{"dateCode":"20220607","raceId":"city-attorney","title":"CITY ATTORNEY","era":"prec_2012","precincts":{"1101":{"votes":{"DAVID CHIU":192,"Write-in":0},"total":192},"1102":{"votes":{"DAVID CHIU":388,"Write-in":0},"total":388},"1103":{"votes":{"DAVID CHIU":336,"Write-in":0},"total":336},"1106":{"votes":{"DAVID CHIU":589,"Write-in":0},"total":589},"1107":{"votes":{"DAVID CHIU":147,"Write-in":0},"total":147},"1108":{"votes":{"DAVID CHIU":340,"Write-in":0},"total":340},"1109":{"votes":{"DAVID CHIU":257,"Write-in":0},"total":257},"1111":{"votes":{"DAVID CHIU":319,"Write-in":0},"total":319},"1112":{"votes":{"DAVID CHIU":221,"Write-in":0},"total":221},"1113":{"votes":{"DAVID CHIU":229,"Write-in":0},"total":229},"1114":{"votes":{"DAVID CHIU":275,"Write-in":0},"total":275},"1115":{"votes":{"DAVID CHIU":90,"Write-in":0},"total":90},"1116":{"votes":{"DAVID CHIU":198,"Write-in":0},"total":198},"1117":{"votes":{"DAVID CHIU":197,"Write-in":0},"total":197},"1118":{"votes":{"DAVID CHIU":315,"Write-in":0},"total":315},"1119":{"votes":{"DAVID CHIU":236,"Write-in":0},"total":236},"1121":{"votes":{"DAVID CHIU":215,"Write-in":0},"total":215},"1122":{"votes":{"DAVID CHIU":187,"Write-in":0},"total":187},"1123":{"votes":{"DAVID CHIU":205,"Write-in":0},"total":205},"1124":{"votes":{"DAVID CHIU":189,"Write-in":0},"total":189},"1125":{"votes":{"DAVID CHIU":276,"Write-in":0},"total":276},"1126":{"votes":{"DAVID CHIU":254,"Write-in":0},"total":254},"1127":{"votes":{"DAVID CHIU":247,"Write-in":0},"total":247},"1128":{"votes":{"DAVID CHIU":228,"Write-in":0},"total":228},"1129":{"votes":{"DAVID CHIU":263,"Write-in":0},"total":263},"1131":{"votes":{"DAVID CHIU":255,"Write-in":0},"total":255},"1132":{"votes":{"DAVID CHIU":270,"Write-in":0},"total":270},"1133":{"votes":{"DAVID CHIU":279,"Write-in":0},"total":279},"1134":{"votes":{"DAVID CHIU":251,"Write-in":0},"total":251},"1135":{"votes":{"DAVID CHIU":186,"Write-in":0},"total":186},"1136":{"votes":{"DAVID CHIU":255,"Write-in":0},"total":255},"1141":{"votes":{"DAVID CHIU":342,"Write-in":0},"total":342},"1142":{"votes":{"DAVID CHIU":303,"Write-in":0},"total":303},"1143":{"votes":{"DAVID CHIU":282,"Write-in":0},"total":282},"1144":{"votes":{"DAVID CHIU":261,"Write-in":0},"total":261},"1145":{"votes":{"DAVID CHIU":303,"Write-in":0},"total":303},"1146":{"votes":{"DAVID CHIU":298,"Write-in":0},"total":298},"1147":{"votes":{"DAVID CHIU":246,"Write-in":0},"total":246},"1148":{"votes":{"DAVID CHIU":285,"Write-in":0},"total":285},"1149":{"votes":{"DAVID CHIU":280,"Write-in":0},"total":280},"1152":{"votes":{"DAVID CHIU":257,"Write-in":0},"total":257},"1153":{"votes":{"DAVID CHIU":274,"Write-in":0},"total":274},"7001":{"votes":{"DAVID CHIU":228,"Write-in":0},"total":228},"7002":{"votes":{"DAVID CHIU":184,"Write-in":0},"total":184},"7003":{"votes":{"DAVID CHIU":345,"Write-in":0},"total":345},"7004":{"votes":{"DAVID CHIU":391,"Write-in":0},"total":391},"7005":{"votes":{"DAVID CHIU":327,"Write-in":0},"total":327},"7006":{"votes":{"DAVID CHIU":257,"Write-in":0},"total":257},"7007":{"votes":{"DAVID CHIU":353,"Write-in":0},"total":353},"7008":{"votes":{"DAVID CHIU":376,"Write-in":0},"total":376},"7009":{"votes":{"DAVID CHIU":266,"Write-in":0},"total":266},"7011":{"votes":{"DAVID CHIU":208,"Write-in":0},"total":208},"7012":{"votes":{"DAVID CHIU":451,"Write-in":0},"total":451},"7013":{"votes":{"DAVID CHIU":352,"Write-in":0},"total":352},"7014":{"votes":{"DAVID CHIU":266,"Write-in":0},"total":266},"7016":{"votes":{"DAVID CHIU":161,"Write-in":0},"total":161},"7017":{"votes":{"DAVID CHIU":134,"Write-in":0},"total":134},"7018":{"votes":{"DAVID CHIU":266,"Write-in":0},"total":266},"7019":{"votes":{"DAVID CHIU":285,"Write-in":0},"total":285},"7021":{"votes":{"DAVID CHIU":193,"Write-in":0},"total":193},"7022":{"votes":{"DAVID CHIU":214,"Write-in":0},"total":214},"7023":{"votes":{"DAVID CHIU":248,"Write-in":0},"total":248},"7024":{"votes":{"DAVID CHIU":37,"Write-in":0},"total":37},"7025":{"votes":{"DAVID CHIU":68,"Write-in":0},"total":68},"7026":{"votes":{"DAVID CHIU":287,"Write-in":0},"total":287},"7027":{"votes":{"DAVID CHIU":219,"Write-in":0},"total":219},"7028":{"votes":{"DAVID CHIU":167,"Write-in":0},"total":167},"7029":{"votes":{"DAVID CHIU":136,"Write-in":0},"total":136},"7030":{"votes":{"DAVID CHIU":223,"Write-in":0},"total":223},"7031":{"votes":{"DAVID CHIU":194,"Write-in":0},"total":194},"7032":{"votes":{"DAVID CHIU":188,"Write-in":0},"total":188},"7033":{"votes":{"DAVID CHIU":161,"Write-in":0},"total":161},"7034":{"votes":{"DAVID CHIU":107,"Write-in":0},"total":107},"7035":{"votes":{"DAVID CHIU":219,"Write-in":0},"total":219},"7036":{"votes":{"DAVID CHIU":190,"Write-in":0},"total":190},"7037":{"votes":{"DAVID CHIU":39,"Write-in":0},"total":39},"7038":{"votes":{"DAVID CHIU":199,"Write-in":0},"total":199},"7039":{"votes":{"DAVID CHIU":199,"Write-in":0},"total":199},"7042":{"votes":{"DAVID CHIU":143,"Write-in":0},"total":143},"7043":{"votes":{"DAVID CHIU":209,"Write-in":0},"total":209},"7044":{"votes":{"DAVID CHIU":123,"Write-in":0},"total":123},"7045":{"votes":{"DAVID CHIU":219,"Write-in":0},"total":219},"7046":{"votes":{"DAVID CHIU":126,"Write-in":0},"total":126},"7047":{"votes":{"DAVID CHIU":262,"Write-in":0},"total":262},"7048":{"votes":{"DAVID CHIU":189,"Write-in":0},"total":189},"7049":{"votes":{"DAVID CHIU":228,"Write-in":0},"total":228},"7051":{"votes":{"DAVID CHIU":248,"Write-in":0},"total":248},"7052":{"votes":{"DAVID CHIU":261,"Write-in":0},"total":261},"7053":{"votes":{"DAVID CHIU":158,"Write-in":0},"total":158},"7054":{"votes":{"DAVID CHIU":184,"Write-in":0},"total":184},"7055":{"votes":{"DAVID CHIU":247,"Write-in":0},"total":247},"7056":{"votes":{"DAVID CHIU":237,"Write-in":0},"total":237},"7201":{"votes":{"DAVID CHIU":287,"Write-in":0},"total":287},"7202":{"votes":{"DAVID CHIU":323,"Write-in":0},"total":323},"7203":{"votes":{"DAVID CHIU":251,"Write-in":0},"total":251},"7204":{"votes":{"DAVID CHIU":322,"Write-in":0},"total":322},"7205":{"votes":{"DAVID CHIU":321,"Write-in":0},"total":321},"7206":{"votes":{"DAVID CHIU":126,"Write-in":0},"total":126},"7207":{"votes":{"DAVID CHIU":66,"Write-in":0},"total":66},"7208":{"votes":{"DAVID CHIU":212,"Write-in":0},"total":212},"7209":{"votes":{"DAVID CHIU":454,"Write-in":0},"total":454},"7301":{"votes":{"DAVID CHIU":246,"Write-in":0},"total":246},"7302":{"votes":{"DAVID CHIU":312,"Write-in":0},"total":312},"7303":{"votes":{"DAVID CHIU":236,"Write-in":0},"total":236},"7304":{"votes":{"DAVID CHIU":333,"Write-in":0},"total":333},"7305":{"votes":{"DAVID CHIU":324,"Write-in":0},"total":324},"7306":{"votes":{"DAVID CHIU":302,"Write-in":0},"total":302},"7307":{"votes":{"DAVID CHIU":250,"Write-in":0},"total":250},"7308":{"votes":{"DAVID CHIU":219,"Write-in":0},"total":219},"7309":{"votes":{"DAVID CHIU":235,"Write-in":0},"total":235},"7311":{"votes":{"DAVID CHIU":257,"Write-in":0},"total":257},"7312":{"votes":{"DAVID CHIU":145,"Write-in":0},"total":145},"7313":{"votes":{"DAVID CHIU":401,"Write-in":0},"total":401},"7314":{"votes":{"DAVID CHIU":150,"Write-in":0},"total":150},"7315":{"votes":{"DAVID CHIU":187,"Write-in":0},"total":187},"7316":{"votes":{"DAVID CHIU":202,"Write-in":0},"total":202},"7317":{"votes":{"DAVID CHIU":308,"Write-in":0},"total":308},"7318":{"votes":{"DAVID CHIU":212,"Write-in":0},"total":212},"7319":{"votes":{"DAVID CHIU":267,"Write-in":0},"total":267},"7321":{"votes":{"DAVID CHIU":180,"Write-in":0},"total":180},"7322":{"votes":{"DAVID CHIU":233,"Write-in":0},"total":233},"7323":{"votes":{"DAVID CHIU":272,"Write-in":0},"total":272},"7324":{"votes":{"DAVID CHIU":185,"Write-in":0},"total":185},"7325":{"votes":{"DAVID CHIU":270,"Write-in":0},"total":270},"7326":{"votes":{"DAVID CHIU":230,"Write-in":0},"total":230},"7327":{"votes":{"DAVID CHIU":190,"Write-in":0},"total":190},"7328":{"votes":{"DAVID CHIU":222,"Write-in":0},"total":222},"7329":{"votes":{"DAVID CHIU":163,"Write-in":0},"total":163},"7331":{"votes":{"DAVID CHIU":317,"Write-in":0},"total":317},"7332":{"votes":{"DAVID CHIU":188,"Write-in":0},"total":188},"7333":{"votes":{"DAVID CHIU":300,"Write-in":0},"total":300},"7334":{"votes":{"DAVID CHIU":208,"Write-in":0},"total":208},"7335":{"votes":{"DAVID CHIU":302,"Write-in":0},"total":302},"7336":{"votes":{"DAVID CHIU":306,"Write-in":0},"total":306},"7337":{"votes":{"DAVID CHIU":295,"Write-in":0},"total":295},"7338":{"votes":{"DAVID CHIU":282,"Write-in":0},"total":282},"7339":{"votes":{"DAVID CHIU":198,"Write-in":0},"total":198},"7341":{"votes":{"DAVID CHIU":225,"Write-in":0},"total":225},"7342":{"votes":{"DAVID CHIU":279,"Write-in":0},"total":279},"7343":{"votes":{"DAVID CHIU":175,"Write-in":0},"total":175},"7344":{"votes":{"DAVID CHIU":322,"Write-in":0},"total":322},"7345":{"votes":{"DAVID CHIU":293,"Write-in":0},"total":293},"7346":{"votes":{"DAVID CHIU":219,"Write-in":0},"total":219},"7347":{"votes":{"DAVID CHIU":236,"Write-in":0},"total":236},"7348":{"votes":{"DAVID CHIU":183,"Write-in":0},"total":183},"7349":{"votes":{"DAVID CHIU":243,"Write-in":0},"total":243},"7501":{"votes":{"DAVID CHIU":184,"Write-in":0},"total":184},"7502":{"votes":{"DAVID CHIU":261,"Write-in":0},"total":261},"7503":{"votes":{"DAVID CHIU":226,"Write-in":0},"total":226},"7504":{"votes":{"DAVID CHIU":129,"Write-in":0},"total":129},"7505":{"votes":{"DAVID CHIU":336,"Write-in":0},"total":336},"7506":{"votes":{"DAVID CHIU":244,"Write-in":0},"total":244},"7507":{"votes":{"DAVID CHIU":244,"Write-in":0},"total":244},"7508":{"votes":{"DAVID CHIU":278,"Write-in":0},"total":278},"7512":{"votes":{"DAVID CHIU":175,"Write-in":0},"total":175},"7513":{"votes":{"DAVID CHIU":203,"Write-in":0},"total":203},"7514":{"votes":{"DAVID CHIU":170,"Write-in":0},"total":170},"7515":{"votes":{"DAVID CHIU":227,"Write-in":0},"total":227},"7516":{"votes":{"DAVID CHIU":341,"Write-in":0},"total":341},"7517":{"votes":{"DAVID CHIU":292,"Write-in":0},"total":292},"7518":{"votes":{"DAVID CHIU":314,"Write-in":0},"total":314},"7519":{"votes":{"DAVID CHIU":201,"Write-in":0},"total":201},"7521":{"votes":{"DAVID CHIU":257,"Write-in":0},"total":257},"7522":{"votes":{"DAVID CHIU":268,"Write-in":0},"total":268},"7523":{"votes":{"DAVID CHIU":238,"Write-in":0},"total":238},"7524":{"votes":{"DAVID CHIU":164,"Write-in":0},"total":164},"7525":{"votes":{"DAVID CHIU":181,"Write-in":0},"total":181},"7526":{"votes":{"DAVID CHIU":302,"Write-in":0},"total":302},"7529":{"votes":{"DAVID CHIU":262,"Write-in":0},"total":262},"7531":{"votes":{"DAVID CHIU":263,"Write-in":0},"total":263},"7532":{"votes":{"DAVID CHIU":249,"Write-in":0},"total":249},"7533":{"votes":{"DAVID CHIU":273,"Write-in":0},"total":273},"7534":{"votes":{"DAVID CHIU":316,"Write-in":0},"total":316},"7535":{"votes":{"DAVID CHIU":286,"Write-in":0},"total":286},"7536":{"votes":{"DAVID CHIU":481,"Write-in":0},"total":481},"7537":{"votes":{"DAVID CHIU":45,"Write-in":0},"total":45},"7538":{"votes":{"DAVID CHIU":266,"Write-in":0},"total":266},"7539":{"votes":{"DAVID CHIU":285,"Write-in":0},"total":285},"7541":{"votes":{"DAVID CHIU":254,"Write-in":0},"total":254},"7542":{"votes":{"DAVID CHIU":244,"Write-in":0},"total":244},"7543":{"votes":{"DAVID CHIU":284,"Write-in":0},"total":284},"7544":{"votes":{"DAVID CHIU":323,"Write-in":0},"total":323},"7545":{"votes":{"DAVID CHIU":260,"Write-in":0},"total":260},"7546":{"votes":{"DAVID CHIU":352,"Write-in":0},"total":352},"7547":{"votes":{"DAVID CHIU":277,"Write-in":0},"total":277},"7548":{"votes":{"DAVID CHIU":444,"Write-in":0},"total":444},"7549":{"votes":{"DAVID CHIU":289,"Write-in":0},"total":289},"7551":{"votes":{"DAVID CHIU":262,"Write-in":0},"total":262},"7552":{"votes":{"DAVID CHIU":598,"Write-in":0},"total":598},"7554":{"votes":{"DAVID CHIU":316,"Write-in":0},"total":316},"7555":{"votes":{"DAVID CHIU":352,"Write-in":0},"total":352},"7601":{"votes":{"DAVID CHIU":135,"Write-in":0},"total":135},"7602":{"votes":{"DAVID CHIU":169,"Write-in":0},"total":169},"7603":{"votes":{"DAVID CHIU":185,"Write-in":0},"total":185},"7604":{"votes":{"DAVID CHIU":181,"Write-in":0},"total":181},"7605":{"votes":{"DAVID CHIU":162,"Write-in":0},"total":162},"7606":{"votes":{"DAVID CHIU":155,"Write-in":0},"total":155},"7607":{"votes":{"DAVID CHIU":208,"Write-in":0},"total":208},"7608":{"votes":{"DAVID CHIU":94,"Write-in":0},"total":94},"7609":{"votes":{"DAVID CHIU":216,"Write-in":0},"total":216},"7611":{"votes":{"DAVID CHIU":192,"Write-in":0},"total":192},"7612":{"votes":{"DAVID CHIU":181,"Write-in":0},"total":181},"7613":{"votes":{"DAVID CHIU":199,"Write-in":0},"total":199},"7614":{"votes":{"DAVID CHIU":150,"Write-in":0},"total":150},"7615":{"votes":{"DAVID CHIU":147,"Write-in":0},"total":147},"7616":{"votes":{"DAVID CHIU":205,"Write-in":0},"total":205},"7617":{"votes":{"DAVID CHIU":207,"Write-in":0},"total":207},"7618":{"votes":{"DAVID CHIU":244,"Write-in":0},"total":244},"7619":{"votes":{"DAVID CHIU":378,"Write-in":0},"total":378},"7621":{"votes":{"DAVID CHIU":364,"Write-in":0},"total":364},"7622":{"votes":{"DAVID CHIU":132,"Write-in":0},"total":132},"7623":{"votes":{"DAVID CHIU":201,"Write-in":0},"total":201},"7624":{"votes":{"DAVID CHIU":154,"Write-in":0},"total":154},"7625":{"votes":{"DAVID CHIU":300,"Write-in":0},"total":300},"7626":{"votes":{"DAVID CHIU":307,"Write-in":0},"total":307},"7627":{"votes":{"DAVID CHIU":131,"Write-in":0},"total":131},"7628":{"votes":{"DAVID CHIU":219,"Write-in":0},"total":219},"7629":{"votes":{"DAVID CHIU":229,"Write-in":0},"total":229},"7631":{"votes":{"DAVID CHIU":328,"Write-in":0},"total":328},"7632":{"votes":{"DAVID CHIU":336,"Write-in":0},"total":336},"7633":{"votes":{"DAVID CHIU":237,"Write-in":0},"total":237},"7634":{"votes":{"DAVID CHIU":234,"Write-in":0},"total":234},"7635":{"votes":{"DAVID CHIU":226,"Write-in":0},"total":226},"7636":{"votes":{"DAVID CHIU":195,"Write-in":0},"total":195},"7637":{"votes":{"DAVID CHIU":252,"Write-in":0},"total":252},"7638":{"votes":{"DAVID CHIU":267,"Write-in":0},"total":267},"7639":{"votes":{"DAVID CHIU":305,"Write-in":0},"total":305},"7641":{"votes":{"DAVID CHIU":346,"Write-in":0},"total":346},"7642":{"votes":{"DAVID CHIU":170,"Write-in":0},"total":170},"7643":{"votes":{"DAVID CHIU":308,"Write-in":0},"total":308},"7644":{"votes":{"DAVID CHIU":304,"Write-in":0},"total":304},"7645":{"votes":{"DAVID CHIU":213,"Write-in":0},"total":213},"7646":{"votes":{"DAVID CHIU":329,"Write-in":0},"total":329},"7647":{"votes":{"DAVID CHIU":125,"Write-in":0},"total":125},"7649":{"votes":{"DAVID CHIU":205,"Write-in":0},"total":205},"7651":{"votes":{"DAVID CHIU":270,"Write-in":0},"total":270},"7652":{"votes":{"DAVID CHIU":200,"Write-in":0},"total":200},"7653":{"votes":{"DAVID CHIU":237,"Write-in":0},"total":237},"7654":{"votes":{"DAVID CHIU":160,"Write-in":0},"total":160},"7655":{"votes":{"DAVID CHIU":290,"Write-in":0},"total":290},"7656":{"votes":{"DAVID CHIU":219,"Write-in":0},"total":219},"7657":{"votes":{"DAVID CHIU":218,"Write-in":0},"total":218},"7701":{"votes":{"DAVID CHIU":391,"Write-in":0},"total":391},"7702":{"votes":{"DAVID CHIU":291,"Write-in":0},"total":291},"7704":{"votes":{"DAVID CHIU":453,"Write-in":0},"total":453},"7705":{"votes":{"DAVID CHIU":272,"Write-in":0},"total":272},"7706":{"votes":{"DAVID CHIU":423,"Write-in":0},"total":423},"7707":{"votes":{"DAVID CHIU":432,"Write-in":0},"total":432},"7708":{"votes":{"DAVID CHIU":382,"Write-in":0},"total":382},"7709":{"votes":{"DAVID CHIU":169,"Write-in":0},"total":169},"7711":{"votes":{"DAVID CHIU":381,"Write-in":0},"total":381},"7712":{"votes":{"DAVID CHIU":187,"Write-in":0},"total":187},"7801":{"votes":{"DAVID CHIU":240,"Write-in":0},"total":240},"7802":{"votes":{"DAVID CHIU":413,"Write-in":0},"total":413},"7803":{"votes":{"DAVID CHIU":128,"Write-in":0},"total":128},"7804":{"votes":{"DAVID CHIU":285,"Write-in":0},"total":285},"7805":{"votes":{"DAVID CHIU":352,"Write-in":0},"total":352},"7806":{"votes":{"DAVID CHIU":282,"Write-in":0},"total":282},"7807":{"votes":{"DAVID CHIU":334,"Write-in":0},"total":334},"7808":{"votes":{"DAVID CHIU":232,"Write-in":0},"total":232},"7809":{"votes":{"DAVID CHIU":273,"Write-in":0},"total":273},"7811":{"votes":{"DAVID CHIU":214,"Write-in":0},"total":214},"7812":{"votes":{"DAVID CHIU":320,"Write-in":0},"total":320},"7813":{"votes":{"DAVID CHIU":390,"Write-in":0},"total":390},"7814":{"votes":{"DAVID CHIU":204,"Write-in":0},"total":204},"7815":{"votes":{"DAVID CHIU":368,"Write-in":0},"total":368},"7816":{"votes":{"DAVID CHIU":402,"Write-in":0},"total":402},"7817":{"votes":{"DAVID CHIU":356,"Write-in":0},"total":356},"7818":{"votes":{"DAVID CHIU":312,"Write-in":0},"total":312},"7819":{"votes":{"DAVID CHIU":278,"Write-in":0},"total":278},"7821":{"votes":{"DAVID CHIU":445,"Write-in":0},"total":445},"7822":{"votes":{"DAVID CHIU":334,"Write-in":0},"total":334},"7823":{"votes":{"DAVID CHIU":385,"Write-in":0},"total":385},"7824":{"votes":{"DAVID CHIU":286,"Write-in":0},"total":286},"7825":{"votes":{"DAVID CHIU":219,"Write-in":0},"total":219},"7826":{"votes":{"DAVID CHIU":234,"Write-in":0},"total":234},"7827":{"votes":{"DAVID CHIU":244,"Write-in":0},"total":244},"7828":{"votes":{"DAVID CHIU":402,"Write-in":0},"total":402},"7829":{"votes":{"DAVID CHIU":395,"Write-in":0},"total":395},"7831":{"votes":{"DAVID CHIU":403,"Write-in":0},"total":403},"7832":{"votes":{"DAVID CHIU":329,"Write-in":0},"total":329},"7833":{"votes":{"DAVID CHIU":259,"Write-in":0},"total":259},"7834":{"votes":{"DAVID CHIU":254,"Write-in":0},"total":254},"7835":{"votes":{"DAVID CHIU":342,"Write-in":0},"total":342},"7836":{"votes":{"DAVID CHIU":407,"Write-in":0},"total":407},"7837":{"votes":{"DAVID CHIU":403,"Write-in":0},"total":403},"7838":{"votes":{"DAVID CHIU":418,"Write-in":0},"total":418},"7839":{"votes":{"DAVID CHIU":372,"Write-in":0},"total":372},"7841":{"votes":{"DAVID CHIU":379,"Write-in":0},"total":379},"7842":{"votes":{"DAVID CHIU":322,"Write-in":0},"total":322},"7843":{"votes":{"DAVID CHIU":244,"Write-in":0},"total":244},"7844":{"votes":{"DAVID CHIU":230,"Write-in":0},"total":230},"7845":{"votes":{"DAVID CHIU":407,"Write-in":0},"total":407},"7846":{"votes":{"DAVID CHIU":336,"Write-in":0},"total":336},"7847":{"votes":{"DAVID CHIU":367,"Write-in":0},"total":367},"7848":{"votes":{"DAVID CHIU":380,"Write-in":0},"total":380},"7849":{"votes":{"DAVID CHIU":354,"Write-in":0},"total":354},"7851":{"votes":{"DAVID CHIU":269,"Write-in":0},"total":269},"7852":{"votes":{"DAVID CHIU":311,"Write-in":0},"total":311},"7853":{"votes":{"DAVID CHIU":356,"Write-in":0},"total":356},"7854":{"votes":{"DAVID CHIU":362,"Write-in":0},"total":362},"7855":{"votes":{"DAVID CHIU":359,"Write-in":0},"total":359},"7856":{"votes":{"DAVID CHIU":348,"Write-in":0},"total":348},"7857":{"votes":{"DAVID CHIU":316,"Write-in":0},"total":316},"7858":{"votes":{"DAVID CHIU":254,"Write-in":0},"total":254},"7859":{"votes":{"DAVID CHIU":379,"Write-in":0},"total":379},"7861":{"votes":{"DAVID CHIU":383,"Write-in":0},"total":383},"7862":{"votes":{"DAVID CHIU":379,"Write-in":0},"total":379},"7863":{"votes":{"DAVID CHIU":333,"Write-in":0},"total":333},"7864":{"votes":{"DAVID CHIU":307,"Write-in":0},"total":307},"7865":{"votes":{"DAVID CHIU":288,"Write-in":0},"total":288},"7866":{"votes":{"DAVID CHIU":398,"Write-in":0},"total":398},"7867":{"votes":{"DAVID CHIU":448,"Write-in":0},"total":448},"7868":{"votes":{"DAVID CHIU":330,"Write-in":0},"total":330},"7869":{"votes":{"DAVID CHIU":409,"Write-in":0},"total":409},"7871":{"votes":{"DAVID CHIU":337,"Write-in":0},"total":337},"7872":{"votes":{"DAVID CHIU":412,"Write-in":0},"total":412},"7873":{"votes":{"DAVID CHIU":406,"Write-in":0},"total":406},"7874":{"votes":{"DAVID CHIU":175,"Write-in":0},"total":175},"7875":{"votes":{"DAVID CHIU":170,"Write-in":0},"total":170},"7876":{"votes":{"DAVID CHIU":185,"Write-in":0},"total":185},"7901":{"votes":{"DAVID CHIU":133,"Write-in":0},"total":133},"7902":{"votes":{"DAVID CHIU":207,"Write-in":0},"total":207},"7903":{"votes":{"DAVID CHIU":182,"Write-in":0},"total":182},"7904":{"votes":{"DAVID CHIU":198,"Write-in":0},"total":198},"7905":{"votes":{"DAVID CHIU":313,"Write-in":0},"total":313},"7906":{"votes":{"DAVID CHIU":193,"Write-in":0},"total":193},"7907":{"votes":{"DAVID CHIU":290,"Write-in":0},"total":290},"7908":{"votes":{"DAVID CHIU":252,"Write-in":0},"total":252},"7909":{"votes":{"DAVID CHIU":229,"Write-in":0},"total":229},"7911":{"votes":{"DAVID CHIU":249,"Write-in":0},"total":249},"7912":{"votes":{"DAVID CHIU":300,"Write-in":0},"total":300},"7913":{"votes":{"DAVID CHIU":259,"Write-in":0},"total":259},"7914":{"votes":{"DAVID CHIU":278,"Write-in":0},"total":278},"7915":{"votes":{"DAVID CHIU":240,"Write-in":0},"total":240},"7916":{"votes":{"DAVID CHIU":264,"Write-in":0},"total":264},"7917":{"votes":{"DAVID CHIU":249,"Write-in":0},"total":249},"7918":{"votes":{"DAVID CHIU":233,"Write-in":0},"total":233},"7919":{"votes":{"DAVID CHIU":263,"Write-in":0},"total":263},"7921":{"votes":{"DAVID CHIU":197,"Write-in":0},"total":197},"7922":{"votes":{"DAVID CHIU":253,"Write-in":0},"total":253},"7923":{"votes":{"DAVID CHIU":251,"Write-in":0},"total":251},"7924":{"votes":{"DAVID CHIU":205,"Write-in":0},"total":205},"7925":{"votes":{"DAVID CHIU":166,"Write-in":0},"total":166},"7926":{"votes":{"DAVID CHIU":255,"Write-in":0},"total":255},"7927":{"votes":{"DAVID CHIU":309,"Write-in":0},"total":309},"7928":{"votes":{"DAVID CHIU":366,"Write-in":0},"total":366},"7929":{"votes":{"DAVID CHIU":374,"Write-in":0},"total":374},"7931":{"votes":{"DAVID CHIU":302,"Write-in":0},"total":302},"7932":{"votes":{"DAVID CHIU":250,"Write-in":0},"total":250},"7934":{"votes":{"DAVID CHIU":329,"Write-in":0},"total":329},"7935":{"votes":{"DAVID CHIU":388,"Write-in":0},"total":388},"7936":{"votes":{"DAVID CHIU":390,"Write-in":0},"total":390},"7937":{"votes":{"DAVID CHIU":395,"Write-in":0},"total":395},"7938":{"votes":{"DAVID CHIU":230,"Write-in":0},"total":230},"7939":{"votes":{"DAVID CHIU":275,"Write-in":0},"total":275},"7941":{"votes":{"DAVID CHIU":272,"Write-in":0},"total":272},"7942":{"votes":{"DAVID CHIU":284,"Write-in":0},"total":284},"7943":{"votes":{"DAVID CHIU":335,"Write-in":0},"total":335},"7944":{"votes":{"DAVID CHIU":308,"Write-in":0},"total":308},"7945":{"votes":{"DAVID CHIU":294,"Write-in":0},"total":294},"7946":{"votes":{"DAVID CHIU":318,"Write-in":0},"total":318},"7947":{"votes":{"DAVID CHIU":257,"Write-in":0},"total":257},"7948":{"votes":{"DAVID CHIU":310,"Write-in":0},"total":310},"7949":{"votes":{"DAVID CHIU":213,"Write-in":0},"total":213},"7951":{"votes":{"DAVID CHIU":280,"Write-in":0},"total":280},"7952":{"votes":{"DAVID CHIU":230,"Write-in":0},"total":230},"7953":{"votes":{"DAVID CHIU":230,"Write-in":0},"total":230},"7955":{"votes":{"DAVID CHIU":260,"Write-in":0},"total":260},"7956":{"votes":{"DAVID CHIU":203,"Write-in":0},"total":203},"7957":{"votes":{"DAVID CHIU":191,"Write-in":0},"total":191},"7959":{"votes":{"DAVID CHIU":152,"Write-in":0},"total":152},"9101":{"votes":{"DAVID CHIU":354,"Write-in":0},"total":354},"9102":{"votes":{"DAVID CHIU":370,"Write-in":0},"total":370},"9103":{"votes":{"DAVID CHIU":342,"Write-in":0},"total":342},"9104":{"votes":{"DAVID CHIU":310,"Write-in":0},"total":310},"9105":{"votes":{"DAVID CHIU":343,"Write-in":0},"total":343},"9106":{"votes":{"DAVID CHIU":388,"Write-in":0},"total":388},"9107":{"votes":{"DAVID CHIU":250,"Write-in":0},"total":250},"9108":{"votes":{"DAVID CHIU":255,"Write-in":0},"total":255},"9109":{"votes":{"DAVID CHIU":307,"Write-in":0},"total":307},"9111":{"votes":{"DAVID CHIU":277,"Write-in":0},"total":277},"9112":{"votes":{"DAVID CHIU":331,"Write-in":0},"total":331},"9113":{"votes":{"DAVID CHIU":383,"Write-in":0},"total":383},"9114":{"votes":{"DAVID CHIU":293,"Write-in":0},"total":293},"9115":{"votes":{"DAVID CHIU":274,"Write-in":0},"total":274},"9116":{"votes":{"DAVID CHIU":317,"Write-in":0},"total":317},"9117":{"votes":{"DAVID CHIU":309,"Write-in":0},"total":309},"9118":{"votes":{"DAVID CHIU":326,"Write-in":0},"total":326},"9119":{"votes":{"DAVID CHIU":336,"Write-in":0},"total":336},"9121":{"votes":{"DAVID CHIU":331,"Write-in":0},"total":331},"9122":{"votes":{"DAVID CHIU":329,"Write-in":0},"total":329},"9123":{"votes":{"DAVID CHIU":267,"Write-in":0},"total":267},"9124":{"votes":{"DAVID CHIU":294,"Write-in":0},"total":294},"9125":{"votes":{"DAVID CHIU":292,"Write-in":0},"total":292},"9126":{"votes":{"DAVID CHIU":369,"Write-in":0},"total":369},"9127":{"votes":{"DAVID CHIU":401,"Write-in":0},"total":401},"9128":{"votes":{"DAVID CHIU":323,"Write-in":0},"total":323},"9129":{"votes":{"DAVID CHIU":262,"Write-in":0},"total":262},"9131":{"votes":{"DAVID CHIU":268,"Write-in":0},"total":268},"9132":{"votes":{"DAVID CHIU":291,"Write-in":0},"total":291},"9133":{"votes":{"DAVID CHIU":408,"Write-in":0},"total":408},"9134":{"votes":{"DAVID CHIU":282,"Write-in":0},"total":282},"9135":{"votes":{"DAVID CHIU":291,"Write-in":0},"total":291},"9136":{"votes":{"DAVID CHIU":330,"Write-in":0},"total":330},"9137":{"votes":{"DAVID CHIU":354,"Write-in":0},"total":354},"9138":{"votes":{"DAVID CHIU":346,"Write-in":0},"total":346},"9139":{"votes":{"DAVID CHIU":365,"Write-in":0},"total":365},"9141":{"votes":{"DAVID CHIU":347,"Write-in":0},"total":347},"9142":{"votes":{"DAVID CHIU":322,"Write-in":0},"total":322},"9143":{"votes":{"DAVID CHIU":355,"Write-in":0},"total":355},"9144":{"votes":{"DAVID CHIU":377,"Write-in":0},"total":377},"9145":{"votes":{"DAVID CHIU":350,"Write-in":0},"total":350},"9146":{"votes":{"DAVID CHIU":326,"Write-in":0},"total":326},"9147":{"votes":{"DAVID CHIU":311,"Write-in":0},"total":311},"9148":{"votes":{"DAVID CHIU":340,"Write-in":0},"total":340},"9149":{"votes":{"DAVID CHIU":308,"Write-in":0},"total":308},"9151":{"votes":{"DAVID CHIU":282,"Write-in":0},"total":282},"9152":{"votes":{"DAVID CHIU":114,"Write-in":0},"total":114},"9201":{"votes":{"DAVID CHIU":301,"Write-in":0},"total":301},"9202":{"votes":{"DAVID CHIU":238,"Write-in":0},"total":238},"9203":{"votes":{"DAVID CHIU":302,"Write-in":0},"total":302},"9204":{"votes":{"DAVID CHIU":264,"Write-in":0},"total":264},"9205":{"votes":{"DAVID CHIU":219,"Write-in":0},"total":219},"9206":{"votes":{"DAVID CHIU":275,"Write-in":0},"total":275},"9207":{"votes":{"DAVID CHIU":261,"Write-in":0},"total":261},"9208":{"votes":{"DAVID CHIU":250,"Write-in":0},"total":250},"9209":{"votes":{"DAVID CHIU":229,"Write-in":0},"total":229},"9211":{"votes":{"DAVID CHIU":267,"Write-in":0},"total":267},"9212":{"votes":{"DAVID CHIU":223,"Write-in":0},"total":223},"9213":{"votes":{"DAVID CHIU":236,"Write-in":0},"total":236},"9214":{"votes":{"DAVID CHIU":209,"Write-in":0},"total":209},"9215":{"votes":{"DAVID CHIU":233,"Write-in":0},"total":233},"9216":{"votes":{"DAVID CHIU":244,"Write-in":0},"total":244},"9217":{"votes":{"DAVID CHIU":227,"Write-in":0},"total":227},"9218":{"votes":{"DAVID CHIU":242,"Write-in":0},"total":242},"9219":{"votes":{"DAVID CHIU":222,"Write-in":0},"total":222},"9221":{"votes":{"DAVID CHIU":266,"Write-in":0},"total":266},"9222":{"votes":{"DAVID CHIU":316,"Write-in":0},"total":316},"9223":{"votes":{"DAVID CHIU":225,"Write-in":0},"total":225},"9224":{"votes":{"DAVID CHIU":336,"Write-in":0},"total":336},"9225":{"votes":{"DAVID CHIU":262,"Write-in":0},"total":262},"9226":{"votes":{"DAVID CHIU":264,"Write-in":0},"total":264},"9227":{"votes":{"DAVID CHIU":357,"Write-in":0},"total":357},"9228":{"votes":{"DAVID CHIU":331,"Write-in":0},"total":331},"9229":{"votes":{"DAVID CHIU":268,"Write-in":0},"total":268},"9231":{"votes":{"DAVID CHIU":387,"Write-in":0},"total":387},"9232":{"votes":{"DAVID CHIU":310,"Write-in":0},"total":310},"9233":{"votes":{"DAVID CHIU":333,"Write-in":0},"total":333},"9234":{"votes":{"DAVID CHIU":278,"Write-in":0},"total":278},"9235":{"votes":{"DAVID CHIU":332,"Write-in":0},"total":332},"9236":{"votes":{"DAVID CHIU":249,"Write-in":0},"total":249},"9237":{"votes":{"DAVID CHIU":319,"Write-in":0},"total":319},"9238":{"votes":{"DAVID CHIU":212,"Write-in":0},"total":212},"9239":{"votes":{"DAVID CHIU":305,"Write-in":0},"total":305},"9241":{"votes":{"DAVID CHIU":338,"Write-in":0},"total":338},"9242":{"votes":{"DAVID CHIU":288,"Write-in":0},"total":288},"9243":{"votes":{"DAVID CHIU":228,"Write-in":0},"total":228},"9244":{"votes":{"DAVID CHIU":260,"Write-in":0},"total":260},"9245":{"votes":{"DAVID CHIU":396,"Write-in":0},"total":396},"9246":{"votes":{"DAVID CHIU":251,"Write-in":0},"total":251},"9247":{"votes":{"DAVID CHIU":292,"Write-in":0},"total":292},"9248":{"votes":{"DAVID CHIU":257,"Write-in":0},"total":257},"9249":{"votes":{"DAVID CHIU":334,"Write-in":0},"total":334},"9251":{"votes":{"DAVID CHIU":389,"Write-in":0},"total":389},"9252":{"votes":{"DAVID CHIU":325,"Write-in":0},"total":325},"9253":{"votes":{"DAVID CHIU":260,"Write-in":0},"total":260},"9254":{"votes":{"DAVID CHIU":317,"Write-in":0},"total":317},"9255":{"votes":{"DAVID CHIU":140,"Write-in":0},"total":140},"9256":{"votes":{"DAVID CHIU":137,"Write-in":0},"total":137},"9258":{"votes":{"DAVID CHIU":264,"Write-in":0},"total":264},"9401":{"votes":{"DAVID CHIU":260,"Write-in":0},"total":260},"9402":{"votes":{"DAVID CHIU":308,"Write-in":0},"total":308},"9403":{"votes":{"DAVID CHIU":278,"Write-in":0},"total":278},"9404":{"votes":{"DAVID CHIU":327,"Write-in":0},"total":327},"9405":{"votes":{"DAVID CHIU":288,"Write-in":0},"total":288},"9406":{"votes":{"DAVID CHIU":299,"Write-in":0},"total":299},"9407":{"votes":{"DAVID CHIU":299,"Write-in":0},"total":299},"9408":{"votes":{"DAVID CHIU":220,"Write-in":0},"total":220},"9409":{"votes":{"DAVID CHIU":192,"Write-in":0},"total":192},"9411":{"votes":{"DAVID CHIU":337,"Write-in":0},"total":337},"9412":{"votes":{"DAVID CHIU":270,"Write-in":0},"total":270},"9413":{"votes":{"DAVID CHIU":276,"Write-in":0},"total":276},"9414":{"votes":{"DAVID CHIU":316,"Write-in":0},"total":316},"9415":{"votes":{"DAVID CHIU":274,"Write-in":0},"total":274},"9416":{"votes":{"DAVID CHIU":348,"Write-in":0},"total":348},"9417":{"votes":{"DAVID CHIU":295,"Write-in":0},"total":295},"9418":{"votes":{"DAVID CHIU":298,"Write-in":0},"total":298},"9419":{"votes":{"DAVID CHIU":311,"Write-in":0},"total":311},"9421":{"votes":{"DAVID CHIU":317,"Write-in":0},"total":317},"9422":{"votes":{"DAVID CHIU":359,"Write-in":0},"total":359},"9423":{"votes":{"DAVID CHIU":303,"Write-in":0},"total":303},"9424":{"votes":{"DAVID CHIU":335,"Write-in":0},"total":335},"9425":{"votes":{"DAVID CHIU":345,"Write-in":0},"total":345},"9426":{"votes":{"DAVID CHIU":263,"Write-in":0},"total":263},"9427":{"votes":{"DAVID CHIU":372,"Write-in":0},"total":372},"9428":{"votes":{"DAVID CHIU":317,"Write-in":0},"total":317},"9429":{"votes":{"DAVID CHIU":336,"Write-in":0},"total":336},"9431":{"votes":{"DAVID CHIU":396,"Write-in":0},"total":396},"9432":{"votes":{"DAVID CHIU":345,"Write-in":0},"total":345},"9433":{"votes":{"DAVID CHIU":308,"Write-in":0},"total":308},"9434":{"votes":{"DAVID CHIU":352,"Write-in":0},"total":352},"9435":{"votes":{"DAVID CHIU":349,"Write-in":0},"total":349},"9436":{"votes":{"DAVID CHIU":410,"Write-in":0},"total":410},"9437":{"votes":{"DAVID CHIU":326,"Write-in":0},"total":326},"9438":{"votes":{"DAVID CHIU":343,"Write-in":0},"total":343},"9439":{"votes":{"DAVID CHIU":321,"Write-in":0},"total":321},"9441":{"votes":{"DAVID CHIU":334,"Write-in":0},"total":334},"9442":{"votes":{"DAVID CHIU":347,"Write-in":0},"total":347},"9443":{"votes":{"DAVID CHIU":321,"Write-in":0},"total":321},"9444":{"votes":{"DAVID CHIU":313,"Write-in":0},"total":313},"9445":{"votes":{"DAVID CHIU":322,"Write-in":0},"total":322},"9446":{"votes":{"DAVID CHIU":375,"Write-in":0},"total":375},"9447":{"votes":{"DAVID CHIU":331,"Write-in":0},"total":331},"9448":{"votes":{"DAVID CHIU":315,"Write-in":0},"total":315},"9449":{"votes":{"DAVID CHIU":300,"Write-in":0},"total":300},"9451":{"votes":{"DAVID CHIU":153,"Write-in":0},"total":153},"9452":{"votes":{"DAVID CHIU":331,"Write-in":0},"total":331},"9453":{"votes":{"DAVID CHIU":373,"Write-in":0},"total":373},"9505":{"votes":{"DAVID CHIU":279,"Write-in":0},"total":279},"9506":{"votes":{"DAVID CHIU":219,"Write-in":0},"total":219},"9507":{"votes":{"DAVID CHIU":227,"Write-in":0},"total":227},"9508":{"votes":{"DAVID CHIU":239,"Write-in":0},"total":239},"9509":{"votes":{"DAVID CHIU":210,"Write-in":0},"total":210},"9511":{"votes":{"DAVID CHIU":195,"Write-in":0},"total":195},"9512":{"votes":{"DAVID CHIU":238,"Write-in":0},"total":238},"9513":{"votes":{"DAVID CHIU":232,"Write-in":0},"total":232},"9515":{"votes":{"DAVID CHIU":243,"Write-in":0},"total":243},"9516":{"votes":{"DAVID CHIU":320,"Write-in":0},"total":320},"9517":{"votes":{"DAVID CHIU":251,"Write-in":0},"total":251},"9518":{"votes":{"DAVID CHIU":262,"Write-in":0},"total":262},"9519":{"votes":{"DAVID CHIU":327,"Write-in":0},"total":327},"9521":{"votes":{"DAVID CHIU":293,"Write-in":0},"total":293},"9701":{"votes":{"DAVID CHIU":256,"Write-in":0},"total":256},"9702":{"votes":{"DAVID CHIU":294,"Write-in":0},"total":294},"9703":{"votes":{"DAVID CHIU":406,"Write-in":0},"total":406},"9704":{"votes":{"DAVID CHIU":385,"Write-in":0},"total":385},"9705":{"votes":{"DAVID CHIU":360,"Write-in":0},"total":360},"9707":{"votes":{"DAVID CHIU":349,"Write-in":0},"total":349},"9708":{"votes":{"DAVID CHIU":364,"Write-in":0},"total":364},"9709":{"votes":{"DAVID CHIU":410,"Write-in":0},"total":410},"9711":{"votes":{"DAVID CHIU":306,"Write-in":0},"total":306},"9712":{"votes":{"DAVID CHIU":297,"Write-in":0},"total":297},"9713":{"votes":{"DAVID CHIU":392,"Write-in":0},"total":392},"9714":{"votes":{"DAVID CHIU":412,"Write-in":0},"total":412},"9715":{"votes":{"DAVID CHIU":285,"Write-in":0},"total":285},"9716":{"votes":{"DAVID CHIU":378,"Write-in":0},"total":378},"9717":{"votes":{"DAVID CHIU":421,"Write-in":0},"total":421},"9718":{"votes":{"DAVID CHIU":412,"Write-in":0},"total":412},"9719":{"votes":{"DAVID CHIU":426,"Write-in":0},"total":426},"9721":{"votes":{"DAVID CHIU":318,"Write-in":0},"total":318},"9722":{"votes":{"DAVID CHIU":77,"Write-in":0},"total":77},"9723":{"votes":{"DAVID CHIU":204,"Write-in":0},"total":204},"9724":{"votes":{"DAVID CHIU":410,"Write-in":0},"total":410},"9725":{"votes":{"DAVID CHIU":330,"Write-in":0},"total":330},"9726":{"votes":{"DAVID CHIU":155,"Write-in":0},"total":155},"9727":{"votes":{"DAVID CHIU":192,"Write-in":0},"total":192},"9728":{"votes":{"DAVID CHIU":418,"Write-in":0},"total":418},"9729":{"votes":{"DAVID CHIU":362,"Write-in":0},"total":362},"9731":{"votes":{"DAVID CHIU":251,"Write-in":0},"total":251},"9734":{"votes":{"DAVID CHIU":285,"Write-in":0},"total":285},"9735":{"votes":{"DAVID CHIU":367,"Write-in":0},"total":367},"9736":{"votes":{"DAVID CHIU":293,"Write-in":0},"total":293},"9737":{"votes":{"DAVID CHIU":324,"Write-in":0},"total":324},"9738":{"votes":{"DAVID CHIU":257,"Write-in":0},"total":257},"9739":{"votes":{"DAVID CHIU":172,"Write-in":0},"total":172},"9741":{"votes":{"DAVID CHIU":9,"Write-in":0},"total":9},"9742":{"votes":{"DAVID CHIU":260,"Write-in":0},"total":260},"9743":{"votes":{"DAVID CHIU":294,"Write-in":0},"total":294},"9744":{"votes":{"DAVID CHIU":231,"Write-in":0},"total":231},"9745":{"votes":{"DAVID CHIU":208,"Write-in":0},"total":208},"9746":{"votes":{"DAVID CHIU":367,"Write-in":0},"total":367},"9747":{"votes":{"DAVID CHIU":359,"Write-in":0},"total":359},"9748":{"votes":{"DAVID CHIU":388,"Write-in":0},"total":388},"9749":{"votes":{"DAVID CHIU":254,"Write-in":0},"total":254},"9751":{"votes":{"DAVID CHIU":309,"Write-in":0},"total":309},"9752":{"votes":{"DAVID CHIU":197,"Write-in":0},"total":197},"9753":{"votes":{"DAVID CHIU":496,"Write-in":0},"total":496},"9754":{"votes":{"DAVID CHIU":304,"Write-in":0},"total":304},"9755":{"votes":{"DAVID CHIU":218,"Write-in":0},"total":218},"9756":{"votes":{"DAVID CHIU":178,"Write-in":0},"total":178},"9801":{"votes":{"DAVID CHIU":150,"Write-in":0},"total":150},"9903":{"votes":{"DAVID CHIU":0,"Write-in":0},"total":0},"1104/1105":{"votes":{"DAVID CHIU":298,"Write-in":0},"total":298},"7509/7511":{"votes":{"DAVID CHIU":307,"Write-in":0},"total":307},"7527/7528":{"votes":{"DAVID CHIU":268,"Write-in":0},"total":268},"7556/7557":{"votes":{"DAVID CHIU":483,"Write-in":0},"total":483},"9503/9504":{"votes":{"DAVID CHIU":190,"Write-in":0},"total":190},"9514/9522":{"votes":{"DAVID CHIU":280,"Write-in":0},"total":280}}}