{"dateCode":"20221108","raceId":"measure-j","title":"Measure J","era":"prec_2022","precincts":{"1101":{"votes":{"Yes":197,"No":248},"total":445},"1102":{"votes":{"Yes":183,"No":210},"total":393},"1104":{"votes":{"Yes":324,"No":320},"total":644},"1105":{"votes":{"Yes":227,"No":269},"total":496},"1106":{"votes":{"Yes":146,"No":232},"total":378},"1107":{"votes":{"Yes":178,"No":231},"total":409},"1108":{"votes":{"Yes":328,"No":274},"total":602},"1109":{"votes":{"Yes":273,"No":235},"total":508},"1111":{"votes":{"Yes":147,"No":182},"total":329},"1112":{"votes":{"Yes":242,"No":231},"total":473},"1113":{"votes":{"Yes":221,"No":290},"total":511},"1114":{"votes":{"Yes":126,"No":160},"total":286},"1115":{"votes":{"Yes":188,"No":166},"total":354},"1117":{"votes":{"Yes":271,"No":205},"total":476},"1118":{"votes":{"Yes":258,"No":240},"total":498},"1119":{"votes":{"Yes":175,"No":244},"total":419},"1121":{"votes":{"Yes":236,"No":212},"total":448},"1122":{"votes":{"Yes":156,"No":170},"total":326},"1123":{"votes":{"Yes":160,"No":208},"total":368},"1124":{"votes":{"Yes":220,"No":260},"total":480},"1125":{"votes":{"Yes":267,"No":223},"total":490},"1126":{"votes":{"Yes":306,"No":295},"total":601},"1127":{"votes":{"Yes":303,"No":283},"total":586},"1128":{"votes":{"Yes":301,"No":260},"total":561},"1129":{"votes":{"Yes":271,"No":260},"total":531},"1131":{"votes":{"Yes":246,"No":219},"total":465},"1132":{"votes":{"Yes":306,"No":278},"total":584},"1133":{"votes":{"Yes":305,"No":263},"total":568},"1134":{"votes":{"Yes":329,"No":293},"total":622},"1135":{"votes":{"Yes":223,"No":279},"total":502},"1136":{"votes":{"Yes":282,"No":203},"total":485},"1137":{"votes":{"Yes":242,"No":203},"total":445},"1138":{"votes":{"Yes":209,"No":228},"total":437},"1139":{"votes":{"Yes":234,"No":238},"total":472},"1141":{"votes":{"Yes":277,"No":243},"total":520},"1142":{"votes":{"Yes":253,"No":214},"total":467},"1143":{"votes":{"Yes":274,"No":259},"total":533},"1144":{"votes":{"Yes":247,"No":221},"total":468},"1145":{"votes":{"Yes":181,"No":204},"total":385},"1146":{"votes":{"Yes":234,"No":285},"total":519},"1147":{"votes":{"Yes":255,"No":276},"total":531},"1148":{"votes":{"Yes":244,"No":304},"total":548},"1149":{"votes":{"Yes":259,"No":254},"total":513},"7001":{"votes":{"Yes":420,"No":162},"total":582},"7002":{"votes":{"Yes":417,"No":104},"total":521},"7003":{"votes":{"Yes":408,"No":167},"total":575},"7004":{"votes":{"Yes":411,"No":149},"total":560},"7005":{"votes":{"Yes":421,"No":147},"total":568},"7006":{"votes":{"Yes":504,"No":134},"total":638},"7007":{"votes":{"Yes":288,"No":145},"total":433},"7008":{"votes":{"Yes":354,"No":143},"total":497},"7009":{"votes":{"Yes":442,"No":115},"total":557},"7011":{"votes":{"Yes":221,"No":100},"total":321},"7012":{"votes":{"Yes":397,"No":146},"total":543},"7013":{"votes":{"Yes":307,"No":125},"total":432},"7014":{"votes":{"Yes":253,"No":77},"total":330},"7015":{"votes":{"Yes":301,"No":94},"total":395},"7016":{"votes":{"Yes":249,"No":125},"total":374},"7017":{"votes":{"Yes":151,"No":139},"total":290},"7018":{"votes":{"Yes":127,"No":114},"total":241},"7019":{"votes":{"Yes":244,"No":204},"total":448},"7021":{"votes":{"Yes":195,"No":218},"total":413},"7022":{"votes":{"Yes":187,"No":197},"total":384},"7023":{"votes":{"Yes":133,"No":101},"total":234},"7024":{"votes":{"Yes":170,"No":132},"total":302},"7025":{"votes":{"Yes":158,"No":164},"total":322},"7026":{"votes":{"Yes":70,"No":74},"total":144},"7027":{"votes":{"Yes":156,"No":111},"total":267},"7028":{"votes":{"Yes":192,"No":260},"total":452},"7029":{"votes":{"Yes":180,"No":165},"total":345},"7031":{"votes":{"Yes":159,"No":166},"total":325},"7032":{"votes":{"Yes":118,"No":114},"total":232},"7033":{"votes":{"Yes":109,"No":97},"total":206},"7034":{"votes":{"Yes":99,"No":109},"total":208},"7035":{"votes":{"Yes":231,"No":172},"total":403},"7036":{"votes":{"Yes":180,"No":237},"total":417},"7037":{"votes":{"Yes":249,"No":181},"total":430},"7038":{"votes":{"Yes":147,"No":139},"total":286},"7039":{"votes":{"Yes":153,"No":227},"total":380},"7041":{"votes":{"Yes":108,"No":108},"total":216},"7042":{"votes":{"Yes":151,"No":136},"total":287},"7043":{"votes":{"Yes":166,"No":181},"total":347},"7044":{"votes":{"Yes":146,"No":163},"total":309},"7045":{"votes":{"Yes":160,"No":262},"total":422},"7046":{"votes":{"Yes":172,"No":198},"total":370},"7047":{"votes":{"Yes":178,"No":188},"total":366},"7048":{"votes":{"Yes":203,"No":267},"total":470},"7049":{"votes":{"Yes":176,"No":187},"total":363},"7051":{"votes":{"Yes":96,"No":117},"total":213},"7052":{"votes":{"Yes":192,"No":336},"total":528},"7053":{"votes":{"Yes":136,"No":167},"total":303},"7054":{"votes":{"Yes":220,"No":232},"total":452},"7055":{"votes":{"Yes":121,"No":97},"total":218},"7056":{"votes":{"Yes":103,"No":104},"total":207},"7201":{"votes":{"Yes":319,"No":123},"total":442},"7202":{"votes":{"Yes":358,"No":146},"total":504},"7205":{"votes":{"Yes":178,"No":40},"total":218},"7207":{"votes":{"Yes":436,"No":278},"total":714},"7208":{"votes":{"Yes":564,"No":285},"total":849},"7301":{"votes":{"Yes":275,"No":165},"total":440},"7302":{"votes":{"Yes":514,"No":267},"total":781},"7303":{"votes":{"Yes":411,"No":269},"total":680},"7304":{"votes":{"Yes":382,"No":180},"total":562},"7305":{"votes":{"Yes":425,"No":238},"total":663},"7306":{"votes":{"Yes":360,"No":182},"total":542},"7307":{"votes":{"Yes":487,"No":259},"total":746},"7308":{"votes":{"Yes":271,"No":186},"total":457},"7309":{"votes":{"Yes":350,"No":196},"total":546},"7311":{"votes":{"Yes":133,"No":116},"total":249},"7312":{"votes":{"Yes":329,"No":166},"total":495},"7313":{"votes":{"Yes":436,"No":269},"total":705},"7314":{"votes":{"Yes":391,"No":196},"total":587},"7315":{"votes":{"Yes":426,"No":211},"total":637},"7316":{"votes":{"Yes":309,"No":203},"total":512},"7317":{"votes":{"Yes":158,"No":153},"total":311},"7318":{"votes":{"Yes":141,"No":128},"total":269},"7319":{"votes":{"Yes":368,"No":158},"total":526},"7321":{"votes":{"Yes":461,"No":245},"total":706},"7322":{"votes":{"Yes":415,"No":164},"total":579},"7323":{"votes":{"Yes":374,"No":183},"total":557},"7324":{"votes":{"Yes":362,"No":247},"total":609},"7325":{"votes":{"Yes":188,"No":171},"total":359},"7326":{"votes":{"Yes":269,"No":153},"total":422},"7327":{"votes":{"Yes":419,"No":179},"total":598},"7328":{"votes":{"Yes":338,"No":144},"total":482},"7329":{"votes":{"Yes":387,"No":174},"total":561},"7331":{"votes":{"Yes":393,"No":162},"total":555},"7332":{"votes":{"Yes":384,"No":187},"total":571},"7333":{"votes":{"Yes":372,"No":127},"total":499},"7334":{"votes":{"Yes":409,"No":166},"total":575},"7335":{"votes":{"Yes":490,"No":192},"total":682},"7336":{"votes":{"Yes":322,"No":161},"total":483},"7337":{"votes":{"Yes":203,"No":114},"total":317},"7501":{"votes":{"Yes":317,"No":145},"total":462},"7502":{"votes":{"Yes":338,"No":147},"total":485},"7503":{"votes":{"Yes":413,"No":184},"total":597},"7504":{"votes":{"Yes":629,"No":158},"total":787},"7505":{"votes":{"Yes":357,"No":174},"total":531},"7506":{"votes":{"Yes":401,"No":134},"total":535},"7507":{"votes":{"Yes":222,"No":171},"total":393},"7508":{"votes":{"Yes":549,"No":116},"total":665},"7509":{"votes":{"Yes":338,"No":156},"total":494},"7511":{"votes":{"Yes":233,"No":145},"total":378},"7512":{"votes":{"Yes":414,"No":185},"total":599},"7513":{"votes":{"Yes":643,"No":132},"total":775},"7514":{"votes":{"Yes":545,"No":245},"total":790},"7515":{"votes":{"Yes":410,"No":137},"total":547},"7516":{"votes":{"Yes":413,"No":106},"total":519},"7517":{"votes":{"Yes":703,"No":124},"total":827},"7518":{"votes":{"Yes":548,"No":90},"total":638},"7519":{"votes":{"Yes":671,"No":111},"total":782},"7521":{"votes":{"Yes":601,"No":121},"total":722},"7522":{"votes":{"Yes":531,"No":143},"total":674},"7523":{"votes":{"Yes":434,"No":133},"total":567},"7524":{"votes":{"Yes":207,"No":93},"total":300},"7525":{"votes":{"Yes":303,"No":123},"total":426},"7526":{"votes":{"Yes":296,"No":168},"total":464},"7527":{"votes":{"Yes":369,"No":157},"total":526},"7528":{"votes":{"Yes":173,"No":93},"total":266},"7529":{"votes":{"Yes":238,"No":139},"total":377},"7531":{"votes":{"Yes":208,"No":141},"total":349},"7532":{"votes":{"Yes":312,"No":106},"total":418},"7533":{"votes":{"Yes":286,"No":194},"total":480},"7534":{"votes":{"Yes":247,"No":130},"total":377},"7601":{"votes":{"Yes":390,"No":88},"total":478},"7602":{"votes":{"Yes":407,"No":119},"total":526},"7603":{"votes":{"Yes":500,"No":127},"total":627},"7604":{"votes":{"Yes":369,"No":108},"total":477},"7605":{"votes":{"Yes":280,"No":99},"total":379},"7606":{"votes":{"Yes":290,"No":97},"total":387},"7607":{"votes":{"Yes":298,"No":96},"total":394},"7608":{"votes":{"Yes":494,"No":145},"total":639},"7609":{"votes":{"Yes":364,"No":103},"total":467},"7611":{"votes":{"Yes":234,"No":59},"total":293},"7612":{"votes":{"Yes":322,"No":85},"total":407},"7613":{"votes":{"Yes":281,"No":122},"total":403},"7614":{"votes":{"Yes":216,"No":92},"total":308},"7615":{"votes":{"Yes":265,"No":117},"total":382},"7616":{"votes":{"Yes":248,"No":81},"total":329},"7617":{"votes":{"Yes":265,"No":124},"total":389},"7618":{"votes":{"Yes":256,"No":138},"total":394},"7619":{"votes":{"Yes":300,"No":127},"total":427},"7621":{"votes":{"Yes":261,"No":109},"total":370},"7622":{"votes":{"Yes":496,"No":136},"total":632},"7623":{"votes":{"Yes":138,"No":50},"total":188},"7624":{"votes":{"Yes":222,"No":77},"total":299},"7625":{"votes":{"Yes":222,"No":152},"total":374},"7626":{"votes":{"Yes":262,"No":98},"total":360},"7627":{"votes":{"Yes":269,"No":98},"total":367},"7628":{"votes":{"Yes":234,"No":86},"total":320},"7629":{"votes":{"Yes":338,"No":129},"total":467},"7631":{"votes":{"Yes":388,"No":163},"total":551},"7632":{"votes":{"Yes":354,"No":133},"total":487},"7633":{"votes":{"Yes":304,"No":142},"total":446},"7634":{"votes":{"Yes":398,"No":141},"total":539},"7635":{"votes":{"Yes":418,"No":229},"total":647},"7637":{"votes":{"Yes":251,"No":108},"total":359},"7638":{"votes":{"Yes":264,"No":106},"total":370},"7639":{"votes":{"Yes":332,"No":152},"total":484},"7641":{"votes":{"Yes":373,"No":176},"total":549},"7642":{"votes":{"Yes":350,"No":145},"total":495},"7643":{"votes":{"Yes":337,"No":133},"total":470},"7644":{"votes":{"Yes":196,"No":104},"total":300},"7645":{"votes":{"Yes":206,"No":125},"total":331},"7701":{"votes":{"Yes":333,"No":277},"total":610},"7702":{"votes":{"Yes":343,"No":305},"total":648},"7703":{"votes":{"Yes":387,"No":360},"total":747},"7704":{"votes":{"Yes":316,"No":332},"total":648},"7705":{"votes":{"Yes":321,"No":338},"total":659},"7706":{"votes":{"Yes":366,"No":277},"total":643},"7707":{"votes":{"Yes":408,"No":414},"total":822},"7708":{"votes":{"Yes":240,"No":378},"total":618},"7709":{"votes":{"Yes":363,"No":359},"total":722},"7711":{"votes":{"Yes":437,"No":435},"total":872},"7712":{"votes":{"Yes":183,"No":272},"total":455},"7713":{"votes":{"Yes":245,"No":243},"total":488},"7714":{"votes":{"Yes":283,"No":337},"total":620},"7715":{"votes":{"Yes":434,"No":337},"total":771},"7716":{"votes":{"Yes":443,"No":363},"total":806},"7717":{"votes":{"Yes":342,"No":301},"total":643},"7718":{"votes":{"Yes":301,"No":283},"total":584},"7719":{"votes":{"Yes":368,"No":358},"total":726},"7801":{"votes":{"Yes":564,"No":198},"total":762},"7802":{"votes":{"Yes":622,"No":207},"total":829},"7803":{"votes":{"Yes":544,"No":178},"total":722},"7804":{"votes":{"Yes":535,"No":149},"total":684},"7805":{"votes":{"Yes":671,"No":163},"total":834},"7806":{"votes":{"Yes":569,"No":112},"total":681},"7807":{"votes":{"Yes":543,"No":131},"total":674},"7808":{"votes":{"Yes":519,"No":187},"total":706},"7809":{"votes":{"Yes":588,"No":168},"total":756},"7811":{"votes":{"Yes":495,"No":162},"total":657},"7812":{"votes":{"Yes":637,"No":188},"total":825},"7813":{"votes":{"Yes":690,"No":128},"total":818},"7814":{"votes":{"Yes":560,"No":111},"total":671},"7815":{"votes":{"Yes":660,"No":164},"total":824},"7816":{"votes":{"Yes":534,"No":145},"total":679},"7817":{"votes":{"Yes":564,"No":122},"total":686},"7818":{"votes":{"Yes":421,"No":186},"total":607},"7819":{"votes":{"Yes":460,"No":208},"total":668},"7821":{"votes":{"Yes":616,"No":225},"total":841},"7822":{"votes":{"Yes":586,"No":157},"total":743},"7823":{"votes":{"Yes":567,"No":271},"total":838},"7824":{"votes":{"Yes":566,"No":170},"total":736},"7825":{"votes":{"Yes":612,"No":147},"total":759},"7826":{"votes":{"Yes":326,"No":206},"total":532},"7827":{"votes":{"Yes":368,"No":233},"total":601},"7828":{"votes":{"Yes":454,"No":154},"total":608},"7829":{"votes":{"Yes":550,"No":221},"total":771},"7831":{"votes":{"Yes":574,"No":199},"total":773},"7832":{"votes":{"Yes":607,"No":192},"total":799},"7833":{"votes":{"Yes":563,"No":201},"total":764},"7834":{"votes":{"Yes":559,"No":208},"total":767},"7835":{"votes":{"Yes":526,"No":189},"total":715},"7836":{"votes":{"Yes":470,"No":128},"total":598},"7837":{"votes":{"Yes":509,"No":165},"total":674},"7838":{"votes":{"Yes":483,"No":366},"total":849},"7839":{"votes":{"Yes":353,"No":188},"total":541},"7841":{"votes":{"Yes":564,"No":196},"total":760},"7842":{"votes":{"Yes":603,"No":222},"total":825},"7843":{"votes":{"Yes":561,"No":181},"total":742},"7844":{"votes":{"Yes":453,"No":161},"total":614},"7845":{"votes":{"Yes":486,"No":163},"total":649},"7846":{"votes":{"Yes":298,"No":303},"total":601},"7847":{"votes":{"Yes":467,"No":220},"total":687},"7848":{"votes":{"Yes":354,"No":210},"total":564},"7849":{"votes":{"Yes":515,"No":245},"total":760},"7851":{"votes":{"Yes":531,"No":230},"total":761},"7852":{"votes":{"Yes":495,"No":222},"total":717},"7853":{"votes":{"Yes":197,"No":106},"total":303},"7854":{"votes":{"Yes":200,"No":110},"total":310},"7901":{"votes":{"Yes":359,"No":156},"total":515},"7902":{"votes":{"Yes":413,"No":123},"total":536},"7903":{"votes":{"Yes":479,"No":155},"total":634},"7904":{"votes":{"Yes":291,"No":132},"total":423},"7905":{"votes":{"Yes":331,"No":144},"total":475},"7906":{"votes":{"Yes":482,"No":190},"total":672},"7907":{"votes":{"Yes":538,"No":148},"total":686},"7908":{"votes":{"Yes":390,"No":115},"total":505},"7909":{"votes":{"Yes":437,"No":155},"total":592},"7911":{"votes":{"Yes":443,"No":128},"total":571},"7912":{"votes":{"Yes":551,"No":184},"total":735},"7913":{"votes":{"Yes":574,"No":158},"total":732},"7914":{"votes":{"Yes":495,"No":167},"total":662},"7915":{"votes":{"Yes":431,"No":165},"total":596},"7916":{"votes":{"Yes":454,"No":173},"total":627},"7917":{"votes":{"Yes":456,"No":204},"total":660},"7918":{"votes":{"Yes":407,"No":143},"total":550},"7919":{"votes":{"Yes":478,"No":146},"total":624},"7921":{"votes":{"Yes":414,"No":167},"total":581},"7922":{"votes":{"Yes":317,"No":150},"total":467},"7923":{"votes":{"Yes":376,"No":152},"total":528},"7924":{"votes":{"Yes":429,"No":245},"total":674},"7925":{"votes":{"Yes":542,"No":177},"total":719},"7926":{"votes":{"Yes":330,"No":98},"total":428},"7927":{"votes":{"Yes":515,"No":229},"total":744},"7928":{"votes":{"Yes":561,"No":200},"total":761},"7929":{"votes":{"Yes":397,"No":166},"total":563},"7931":{"votes":{"Yes":394,"No":160},"total":554},"7932":{"votes":{"Yes":565,"No":200},"total":765},"7933":{"votes":{"Yes":582,"No":223},"total":805},"7934":{"votes":{"Yes":378,"No":147},"total":525},"7935":{"votes":{"Yes":442,"No":229},"total":671},"7936":{"votes":{"Yes":505,"No":186},"total":691},"7937":{"votes":{"Yes":419,"No":162},"total":581},"7938":{"votes":{"Yes":328,"No":153},"total":481},"7939":{"votes":{"Yes":301,"No":192},"total":493},"7941":{"votes":{"Yes":288,"No":163},"total":451},"7942":{"votes":{"Yes":201,"No":257},"total":458},"7943":{"votes":{"Yes":222,"No":254},"total":476},"7944":{"votes":{"Yes":211,"No":242},"total":453},"7945":{"votes":{"Yes":167,"No":237},"total":404},"7946":{"votes":{"Yes":242,"No":285},"total":527},"7947":{"votes":{"Yes":173,"No":272},"total":445},"7948":{"votes":{"Yes":274,"No":266},"total":540},"7949":{"votes":{"Yes":140,"No":145},"total":285},"9101":{"votes":{"Yes":293,"No":409},"total":702},"9102":{"votes":{"Yes":280,"No":402},"total":682},"9103":{"votes":{"Yes":282,"No":447},"total":729},"9104":{"votes":{"Yes":312,"No":363},"total":675},"9105":{"votes":{"Yes":383,"No":352},"total":735},"9106":{"votes":{"Yes":361,"No":292},"total":653},"9107":{"votes":{"Yes":355,"No":256},"total":611},"9108":{"votes":{"Yes":343,"No":278},"total":621},"9109":{"votes":{"Yes":349,"No":255},"total":604},"9111":{"votes":{"Yes":419,"No":310},"total":729},"9112":{"votes":{"Yes":287,"No":233},"total":520},"9113":{"votes":{"Yes":417,"No":270},"total":687},"9114":{"votes":{"Yes":354,"No":215},"total":569},"9115":{"votes":{"Yes":458,"No":245},"total":703},"9116":{"votes":{"Yes":366,"No":194},"total":560},"9117":{"votes":{"Yes":440,"No":312},"total":752},"9118":{"votes":{"Yes":439,"No":212},"total":651},"9119":{"votes":{"Yes":323,"No":458},"total":781},"9121":{"votes":{"Yes":259,"No":390},"total":649},"9122":{"votes":{"Yes":236,"No":368},"total":604},"9123":{"votes":{"Yes":316,"No":382},"total":698},"9124":{"votes":{"Yes":368,"No":316},"total":684},"9125":{"votes":{"Yes":300,"No":245},"total":545},"9126":{"votes":{"Yes":405,"No":300},"total":705},"9127":{"votes":{"Yes":435,"No":320},"total":755},"9128":{"votes":{"Yes":421,"No":234},"total":655},"9129":{"votes":{"Yes":489,"No":238},"total":727},"9131":{"votes":{"Yes":420,"No":215},"total":635},"9132":{"votes":{"Yes":501,"No":202},"total":703},"9133":{"votes":{"Yes":269,"No":413},"total":682},"9134":{"votes":{"Yes":356,"No":440},"total":796},"9135":{"votes":{"Yes":337,"No":381},"total":718},"9136":{"votes":{"Yes":332,"No":412},"total":744},"9137":{"votes":{"Yes":374,"No":429},"total":803},"9138":{"votes":{"Yes":405,"No":268},"total":673},"9139":{"votes":{"Yes":372,"No":304},"total":676},"9141":{"votes":{"Yes":483,"No":280},"total":763},"9142":{"votes":{"Yes":593,"No":216},"total":809},"9143":{"votes":{"Yes":539,"No":195},"total":734},"9144":{"votes":{"Yes":528,"No":181},"total":709},"9145":{"votes":{"Yes":478,"No":236},"total":714},"9146":{"votes":{"Yes":495,"No":230},"total":725},"9201":{"votes":{"Yes":472,"No":192},"total":664},"9202":{"votes":{"Yes":401,"No":155},"total":556},"9203":{"votes":{"Yes":439,"No":319},"total":758},"9204":{"votes":{"Yes":414,"No":277},"total":691},"9205":{"votes":{"Yes":340,"No":250},"total":590},"9206":{"votes":{"Yes":351,"No":193},"total":544},"9207":{"votes":{"Yes":375,"No":219},"total":594},"9208":{"votes":{"Yes":402,"No":270},"total":672},"9209":{"votes":{"Yes":374,"No":281},"total":655},"9211":{"votes":{"Yes":386,"No":197},"total":583},"9212":{"votes":{"Yes":384,"No":206},"total":590},"9213":{"votes":{"Yes":415,"No":309},"total":724},"9214":{"votes":{"Yes":436,"No":262},"total":698},"9215":{"votes":{"Yes":456,"No":217},"total":673},"9216":{"votes":{"Yes":358,"No":392},"total":750},"9217":{"votes":{"Yes":483,"No":283},"total":766},"9218":{"votes":{"Yes":512,"No":337},"total":849},"9219":{"votes":{"Yes":425,"No":247},"total":672},"9221":{"votes":{"Yes":428,"No":271},"total":699},"9222":{"votes":{"Yes":509,"No":251},"total":760},"9223":{"votes":{"Yes":457,"No":288},"total":745},"9224":{"votes":{"Yes":560,"No":258},"total":818},"9225":{"votes":{"Yes":369,"No":316},"total":685},"9226":{"votes":{"Yes":436,"No":332},"total":768},"9227":{"votes":{"Yes":484,"No":293},"total":777},"9228":{"votes":{"Yes":441,"No":235},"total":676},"9229":{"votes":{"Yes":549,"No":277},"total":826},"9231":{"votes":{"Yes":570,"No":236},"total":806},"9232":{"votes":{"Yes":514,"No":167},"total":681},"9233":{"votes":{"Yes":413,"No":241},"total":654},"9234":{"votes":{"Yes":352,"No":205},"total":557},"9235":{"votes":{"Yes":383,"No":197},"total":580},"9236":{"votes":{"Yes":554,"No":183},"total":737},"9237":{"votes":{"Yes":570,"No":101},"total":671},"9238":{"votes":{"Yes":276,"No":90},"total":366},"9239":{"votes":{"Yes":359,"No":136},"total":495},"9241":{"votes":{"Yes":545,"No":266},"total":811},"9242":{"votes":{"Yes":506,"No":249},"total":755},"9243":{"votes":{"Yes":409,"No":184},"total":593},"9301":{"votes":{"Yes":351,"No":244},"total":595},"9302":{"votes":{"Yes":451,"No":195},"total":646},"9303":{"votes":{"Yes":421,"No":192},"total":613},"9304":{"votes":{"Yes":457,"No":226},"total":683},"9305":{"votes":{"Yes":412,"No":223},"total":635},"9306":{"votes":{"Yes":339,"No":166},"total":505},"9401":{"votes":{"Yes":435,"No":274},"total":709},"9402":{"votes":{"Yes":418,"No":289},"total":707},"9403":{"votes":{"Yes":345,"No":268},"total":613},"9404":{"votes":{"Yes":340,"No":259},"total":599},"9405":{"votes":{"Yes":314,"No":325},"total":639},"9406":{"votes":{"Yes":384,"No":305},"total":689},"9407":{"votes":{"Yes":423,"No":237},"total":660},"9408":{"votes":{"Yes":362,"No":214},"total":576},"9409":{"votes":{"Yes":265,"No":230},"total":495},"9411":{"votes":{"Yes":355,"No":298},"total":653},"9412":{"votes":{"Yes":342,"No":339},"total":681},"9413":{"votes":{"Yes":311,"No":354},"total":665},"9414":{"votes":{"Yes":356,"No":280},"total":636},"9415":{"votes":{"Yes":310,"No":299},"total":609},"9416":{"votes":{"Yes":361,"No":284},"total":645},"9417":{"votes":{"Yes":322,"No":323},"total":645},"9418":{"votes":{"Yes":278,"No":325},"total":603},"9419":{"votes":{"Yes":245,"No":258},"total":503},"9421":{"votes":{"Yes":290,"No":269},"total":559},"9422":{"votes":{"Yes":311,"No":292},"total":603},"9423":{"votes":{"Yes":345,"No":282},"total":627},"9424":{"votes":{"Yes":339,"No":336},"total":675},"9425":{"votes":{"Yes":206,"No":256},"total":462},"9426":{"votes":{"Yes":250,"No":349},"total":599},"9427":{"votes":{"Yes":254,"No":265},"total":519},"9428":{"votes":{"Yes":430,"No":364},"total":794},"9429":{"votes":{"Yes":295,"No":338},"total":633},"9431":{"votes":{"Yes":234,"No":278},"total":512},"9432":{"votes":{"Yes":236,"No":332},"total":568},"9433":{"votes":{"Yes":283,"No":314},"total":597},"9434":{"votes":{"Yes":268,"No":279},"total":547},"9435":{"votes":{"Yes":311,"No":335},"total":646},"9436":{"votes":{"Yes":272,"No":220},"total":492},"9437":{"votes":{"Yes":314,"No":313},"total":627},"9438":{"votes":{"Yes":271,"No":287},"total":558},"9439":{"votes":{"Yes":235,"No":299},"total":534},"9441":{"votes":{"Yes":260,"No":324},"total":584},"9442":{"votes":{"Yes":258,"No":268},"total":526},"9443":{"votes":{"Yes":352,"No":281},"total":633},"9444":{"votes":{"Yes":285,"No":330},"total":615},"9445":{"votes":{"Yes":222,"No":302},"total":524},"9446":{"votes":{"Yes":204,"No":381},"total":585},"9447":{"votes":{"Yes":249,"No":362},"total":611},"9448":{"votes":{"Yes":317,"No":408},"total":725},"9449":{"votes":{"Yes":98,"No":243},"total":341},"9451":{"votes":{"Yes":239,"No":515},"total":754},"9452":{"votes":{"Yes":236,"No":386},"total":622},"9501":{"votes":{"Yes":630,"No":96},"total":726},"9502":{"votes":{"Yes":582,"No":99},"total":681},"9503":{"votes":{"Yes":523,"No":93},"total":616},"9504":{"votes":{"Yes":775,"No":138},"total":913},"9505":{"votes":{"Yes":777,"No":141},"total":918},"9506":{"votes":{"Yes":672,"No":118},"total":790},"9507":{"votes":{"Yes":504,"No":116},"total":620},"9508":{"votes":{"Yes":696,"No":96},"total":792},"9509":{"votes":{"Yes":586,"No":104},"total":690},"9511":{"votes":{"Yes":167,"No":49},"total":216},"9512":{"votes":{"Yes":200,"No":75},"total":275},"9701":{"votes":{"Yes":536,"No":195},"total":731},"9702":{"votes":{"Yes":475,"No":172},"total":647},"9703":{"votes":{"Yes":524,"No":158},"total":682},"9704":{"votes":{"Yes":428,"No":118},"total":546},"9705":{"votes":{"Yes":461,"No":261},"total":722},"9706":{"votes":{"Yes":518,"No":168},"total":686},"9707":{"votes":{"Yes":495,"No":206},"total":701},"9708":{"votes":{"Yes":500,"No":176},"total":676},"9709":{"votes":{"Yes":464,"No":314},"total":778},"9711":{"votes":{"Yes":340,"No":294},"total":634},"9712":{"votes":{"Yes":515,"No":269},"total":784},"9713":{"votes":{"Yes":444,"No":301},"total":745},"9714":{"votes":{"Yes":390,"No":365},"total":755},"9715":{"votes":{"Yes":352,"No":365},"total":717},"9716":{"votes":{"Yes":371,"No":375},"total":746},"9717":{"votes":{"Yes":326,"No":357},"total":683},"9718":{"votes":{"Yes":327,"No":325},"total":652},"9719":{"votes":{"Yes":442,"No":386},"total":828},"9721":{"votes":{"Yes":225,"No":281},"total":506},"9722":{"votes":{"Yes":132,"No":149},"total":281},"9723":{"votes":{"Yes":212,"No":133},"total":345},"9724":{"votes":{"Yes":272,"No":371},"total":643},"9725":{"votes":{"Yes":252,"No":306},"total":558},"9726":{"votes":{"Yes":269,"No":279},"total":548},"9727":{"votes":{"Yes":263,"No":224},"total":487},"9728":{"votes":{"Yes":256,"No":261},"total":517},"9729":{"votes":{"Yes":187,"No":213},"total":400},"9731":{"votes":{"Yes":163,"No":167},"total":330},"9732":{"votes":{"Yes":454,"No":334},"total":788},"9733":{"votes":{"Yes":372,"No":297},"total":669},"9734":{"votes":{"Yes":477,"No":304},"total":781},"9735":{"votes":{"Yes":397,"No":274},"total":671},"9801":{"votes":{"Yes":529,"No":123},"total":652},"9802":{"votes":{"Yes":696,"No":199},"total":895},"9803":{"votes":{"Yes":573,"No":103},"total":676},"9804":{"votes":{"Yes":701,"No":98},"total":799},"9805":{"votes":{"Yes":610,"No":153},"total":763},"9806":{"votes":{"Yes":636,"No":135},"total":771},"9807":{"votes":{"Yes":465,"No":116},"total":581},"9808":{"votes":{"Yes":330,"No":183},"total":513}}}