{"dateCode":"20241105","raceId":"state-assembly-member-district-17","title":"STATE ASSEMBLY MEMBER, DISTRICT 17","era":"prec_2022","precincts":{"1131":{"votes":{"MATT HANEY\n(DEM)":527,"MANUEL NORIS-BARRERA\n(REP)":148},"total":675},"1132":{"votes":{"MATT HANEY\n(DEM)":593,"MANUEL NORIS-BARRERA\n(REP)":157},"total":750},"1133":{"votes":{"MATT HANEY\n(DEM)":580,"MANUEL NORIS-BARRERA\n(REP)":184},"total":764},"1134":{"votes":{"MATT HANEY\n(DEM)":655,"MANUEL NORIS-BARRERA\n(REP)":148},"total":803},"1135":{"votes":{"MATT HANEY\n(DEM)":477,"MANUEL NORIS-BARRERA\n(REP)":168},"total":645},"1136":{"votes":{"MATT HANEY\n(DEM)":450,"MANUEL NORIS-BARRERA\n(REP)":160},"total":610},"1137":{"votes":{"MATT HANEY\n(DEM)":458,"MANUEL NORIS-BARRERA\n(REP)":141},"total":599},"1138":{"votes":{"MATT HANEY\n(DEM)":417,"MANUEL NORIS-BARRERA\n(REP)":173},"total":590},"1139":{"votes":{"MATT HANEY\n(DEM)":479,"MANUEL NORIS-BARRERA\n(REP)":138},"total":617},"1141":{"votes":{"MATT HANEY\n(DEM)":523,"MANUEL NORIS-BARRERA\n(REP)":160},"total":683},"1142":{"votes":{"MATT HANEY\n(DEM)":455,"MANUEL NORIS-BARRERA\n(REP)":165},"total":620},"1143":{"votes":{"MATT HANEY\n(DEM)":514,"MANUEL NORIS-BARRERA\n(REP)":204},"total":718},"1144":{"votes":{"MATT HANEY\n(DEM)":465,"MANUEL NORIS-BARRERA\n(REP)":180},"total":645},"1145":{"votes":{"MATT HANEY\n(DEM)":439,"MANUEL NORIS-BARRERA\n(REP)":192},"total":631},"1146":{"votes":{"MATT HANEY\n(DEM)":506,"MANUEL NORIS-BARRERA\n(REP)":217},"total":723},"1147":{"votes":{"MATT HANEY\n(DEM)":549,"MANUEL NORIS-BARRERA\n(REP)":176},"total":725},"1148":{"votes":{"MATT HANEY\n(DEM)":522,"MANUEL NORIS-BARRERA\n(REP)":191},"total":713},"1149":{"votes":{"MATT HANEY\n(DEM)":527,"MANUEL NORIS-BARRERA\n(REP)":186},"total":713},"7001":{"votes":{"MATT HANEY\n(DEM)":643,"MANUEL NORIS-BARRERA\n(REP)":80},"total":723},"7002":{"votes":{"MATT HANEY\n(DEM)":639,"MANUEL NORIS-BARRERA\n(REP)":62},"total":701},"7003":{"votes":{"MATT HANEY\n(DEM)":635,"MANUEL NORIS-BARRERA\n(REP)":67},"total":702},"7004":{"votes":{"MATT HANEY\n(DEM)":622,"MANUEL NORIS-BARRERA\n(REP)":72},"total":694},"7005":{"votes":{"MATT HANEY\n(DEM)":619,"MANUEL NORIS-BARRERA\n(REP)":64},"total":683},"7006":{"votes":{"MATT HANEY\n(DEM)":839,"MANUEL NORIS-BARRERA\n(REP)":87},"total":926},"7007":{"votes":{"MATT HANEY\n(DEM)":459,"MANUEL NORIS-BARRERA\n(REP)":56},"total":515},"7008":{"votes":{"MATT HANEY\n(DEM)":558,"MANUEL NORIS-BARRERA\n(REP)":65},"total":623},"7009":{"votes":{"MATT HANEY\n(DEM)":711,"MANUEL NORIS-BARRERA\n(REP)":86},"total":797},"7011":{"votes":{"MATT HANEY\n(DEM)":331,"MANUEL NORIS-BARRERA\n(REP)":66},"total":397},"7012":{"votes":{"MATT HANEY\n(DEM)":596,"MANUEL NORIS-BARRERA\n(REP)":47},"total":643},"7013":{"votes":{"MATT HANEY\n(DEM)":499,"MANUEL NORIS-BARRERA\n(REP)":47},"total":546},"7014":{"votes":{"MATT HANEY\n(DEM)":409,"MANUEL NORIS-BARRERA\n(REP)":49},"total":458},"7015":{"votes":{"MATT HANEY\n(DEM)":450,"MANUEL NORIS-BARRERA\n(REP)":53},"total":503},"7016":{"votes":{"MATT HANEY\n(DEM)":388,"MANUEL NORIS-BARRERA\n(REP)":70},"total":458},"7017":{"votes":{"MATT HANEY\n(DEM)":298,"MANUEL NORIS-BARRERA\n(REP)":121},"total":419},"7018":{"votes":{"MATT HANEY\n(DEM)":278,"MANUEL NORIS-BARRERA\n(REP)":81},"total":359},"7019":{"votes":{"MATT HANEY\n(DEM)":498,"MANUEL NORIS-BARRERA\n(REP)":70},"total":568},"7021":{"votes":{"MATT HANEY\n(DEM)":433,"MANUEL NORIS-BARRERA\n(REP)":162},"total":595},"7022":{"votes":{"MATT HANEY\n(DEM)":376,"MANUEL NORIS-BARRERA\n(REP)":95},"total":471},"7023":{"votes":{"MATT HANEY\n(DEM)":343,"MANUEL NORIS-BARRERA\n(REP)":67},"total":410},"7024":{"votes":{"MATT HANEY\n(DEM)":357,"MANUEL NORIS-BARRERA\n(REP)":74},"total":431},"7025":{"votes":{"MATT HANEY\n(DEM)":400,"MANUEL NORIS-BARRERA\n(REP)":55},"total":455},"7026":{"votes":{"MATT HANEY\n(DEM)":190,"MANUEL NORIS-BARRERA\n(REP)":36},"total":226},"7027":{"votes":{"MATT HANEY\n(DEM)":349,"MANUEL NORIS-BARRERA\n(REP)":66},"total":415},"7028":{"votes":{"MATT HANEY\n(DEM)":366,"MANUEL NORIS-BARRERA\n(REP)":206},"total":572},"7029":{"votes":{"MATT HANEY\n(DEM)":379,"MANUEL NORIS-BARRERA\n(REP)":107},"total":486},"7031":{"votes":{"MATT HANEY\n(DEM)":378,"MANUEL NORIS-BARRERA\n(REP)":66},"total":444},"7032":{"votes":{"MATT HANEY\n(DEM)":286,"MANUEL NORIS-BARRERA\n(REP)":56},"total":342},"7033":{"votes":{"MATT HANEY\n(DEM)":247,"MANUEL NORIS-BARRERA\n(REP)":53},"total":300},"7034":{"votes":{"MATT HANEY\n(DEM)":240,"MANUEL NORIS-BARRERA\n(REP)":52},"total":292},"7035":{"votes":{"MATT HANEY\n(DEM)":492,"MANUEL NORIS-BARRERA\n(REP)":118},"total":610},"7036":{"votes":{"MATT HANEY\n(DEM)":368,"MANUEL NORIS-BARRERA\n(REP)":184},"total":552},"7037":{"votes":{"MATT HANEY\n(DEM)":406,"MANUEL NORIS-BARRERA\n(REP)":174},"total":580},"7038":{"votes":{"MATT HANEY\n(DEM)":280,"MANUEL NORIS-BARRERA\n(REP)":84},"total":364},"7039":{"votes":{"MATT HANEY\n(DEM)":364,"MANUEL NORIS-BARRERA\n(REP)":205},"total":569},"7041":{"votes":{"MATT HANEY\n(DEM)":294,"MANUEL NORIS-BARRERA\n(REP)":92},"total":386},"7042":{"votes":{"MATT HANEY\n(DEM)":273,"MANUEL NORIS-BARRERA\n(REP)":128},"total":401},"7043":{"votes":{"MATT HANEY\n(DEM)":339,"MANUEL NORIS-BARRERA\n(REP)":125},"total":464},"7044":{"votes":{"MATT HANEY\n(DEM)":325,"MANUEL NORIS-BARRERA\n(REP)":118},"total":443},"7045":{"votes":{"MATT HANEY\n(DEM)":378,"MANUEL NORIS-BARRERA\n(REP)":162},"total":540},"7046":{"votes":{"MATT HANEY\n(DEM)":376,"MANUEL NORIS-BARRERA\n(REP)":146},"total":522},"7047":{"votes":{"MATT HANEY\n(DEM)":379,"MANUEL NORIS-BARRERA\n(REP)":132},"total":511},"7048":{"votes":{"MATT HANEY\n(DEM)":439,"MANUEL NORIS-BARRERA\n(REP)":178},"total":617},"7049":{"votes":{"MATT HANEY\n(DEM)":374,"MANUEL NORIS-BARRERA\n(REP)":124},"total":498},"7051":{"votes":{"MATT HANEY\n(DEM)":233,"MANUEL NORIS-BARRERA\n(REP)":81},"total":314},"7052":{"votes":{"MATT HANEY\n(DEM)":469,"MANUEL NORIS-BARRERA\n(REP)":202},"total":671},"7053":{"votes":{"MATT HANEY\n(DEM)":306,"MANUEL NORIS-BARRERA\n(REP)":123},"total":429},"7054":{"votes":{"MATT HANEY\n(DEM)":517,"MANUEL NORIS-BARRERA\n(REP)":114},"total":631},"7055":{"votes":{"MATT HANEY\n(DEM)":249,"MANUEL NORIS-BARRERA\n(REP)":81},"total":330},"7056":{"votes":{"MATT HANEY\n(DEM)":245,"MANUEL NORIS-BARRERA\n(REP)":65},"total":310},"7201":{"votes":{"MATT HANEY\n(DEM)":466,"MANUEL NORIS-BARRERA\n(REP)":88},"total":554},"7202":{"votes":{"MATT HANEY\n(DEM)":565,"MANUEL NORIS-BARRERA\n(REP)":107},"total":672},"7205":{"votes":{"MATT HANEY\n(DEM)":241,"MANUEL NORIS-BARRERA\n(REP)":25},"total":266},"7207":{"votes":{"MATT HANEY\n(DEM)":798,"MANUEL NORIS-BARRERA\n(REP)":118},"total":916},"7208":{"votes":{"MATT HANEY\n(DEM)":976,"MANUEL NORIS-BARRERA\n(REP)":162},"total":1138},"7301":{"votes":{"MATT HANEY\n(DEM)":469,"MANUEL NORIS-BARRERA\n(REP)":147},"total":616},"7302":{"votes":{"MATT HANEY\n(DEM)":790,"MANUEL NORIS-BARRERA\n(REP)":204},"total":994},"7303":{"votes":{"MATT HANEY\n(DEM)":669,"MANUEL NORIS-BARRERA\n(REP)":153},"total":822},"7304":{"votes":{"MATT HANEY\n(DEM)":637,"MANUEL NORIS-BARRERA\n(REP)":140},"total":777},"7305":{"votes":{"MATT HANEY\n(DEM)":767,"MANUEL NORIS-BARRERA\n(REP)":178},"total":945},"7306":{"votes":{"MATT HANEY\n(DEM)":580,"MANUEL NORIS-BARRERA\n(REP)":139},"total":719},"7307":{"votes":{"MATT HANEY\n(DEM)":775,"MANUEL NORIS-BARRERA\n(REP)":200},"total":975},"7308":{"votes":{"MATT HANEY\n(DEM)":490,"MANUEL NORIS-BARRERA\n(REP)":144},"total":634},"7309":{"votes":{"MATT HANEY\n(DEM)":536,"MANUEL NORIS-BARRERA\n(REP)":133},"total":669},"7311":{"votes":{"MATT HANEY\n(DEM)":184,"MANUEL NORIS-BARRERA\n(REP)":46},"total":230},"7312":{"votes":{"MATT HANEY\n(DEM)":573,"MANUEL NORIS-BARRERA\n(REP)":131},"total":704},"7313":{"votes":{"MATT HANEY\n(DEM)":702,"MANUEL NORIS-BARRERA\n(REP)":202},"total":904},"7314":{"votes":{"MATT HANEY\n(DEM)":754,"MANUEL NORIS-BARRERA\n(REP)":140},"total":894},"7315":{"votes":{"MATT HANEY\n(DEM)":728,"MANUEL NORIS-BARRERA\n(REP)":180},"total":908},"7316":{"votes":{"MATT HANEY\n(DEM)":509,"MANUEL NORIS-BARRERA\n(REP)":147},"total":656},"7317":{"votes":{"MATT HANEY\n(DEM)":261,"MANUEL NORIS-BARRERA\n(REP)":93},"total":354},"7318":{"votes":{"MATT HANEY\n(DEM)":247,"MANUEL NORIS-BARRERA\n(REP)":79},"total":326},"7319":{"votes":{"MATT HANEY\n(DEM)":622,"MANUEL NORIS-BARRERA\n(REP)":130},"total":752},"7321":{"votes":{"MATT HANEY\n(DEM)":791,"MANUEL NORIS-BARRERA\n(REP)":138},"total":929},"7322":{"votes":{"MATT HANEY\n(DEM)":695,"MANUEL NORIS-BARRERA\n(REP)":118},"total":813},"7323":{"votes":{"MATT HANEY\n(DEM)":627,"MANUEL NORIS-BARRERA\n(REP)":138},"total":765},"7324":{"votes":{"MATT HANEY\n(DEM)":565,"MANUEL NORIS-BARRERA\n(REP)":190},"total":755},"7325":{"votes":{"MATT HANEY\n(DEM)":314,"MANUEL NORIS-BARRERA\n(REP)":111},"total":425},"7326":{"votes":{"MATT HANEY\n(DEM)":424,"MANUEL NORIS-BARRERA\n(REP)":105},"total":529},"7327":{"votes":{"MATT HANEY\n(DEM)":668,"MANUEL NORIS-BARRERA\n(REP)":140},"total":808},"7328":{"votes":{"MATT HANEY\n(DEM)":615,"MANUEL NORIS-BARRERA\n(REP)":96},"total":711},"7329":{"votes":{"MATT HANEY\n(DEM)":646,"MANUEL NORIS-BARRERA\n(REP)":142},"total":788},"7331":{"votes":{"MATT HANEY\n(DEM)":660,"MANUEL NORIS-BARRERA\n(REP)":117},"total":777},"7332":{"votes":{"MATT HANEY\n(DEM)":681,"MANUEL NORIS-BARRERA\n(REP)":113},"total":794},"7333":{"votes":{"MATT HANEY\n(DEM)":605,"MANUEL NORIS-BARRERA\n(REP)":92},"total":697},"7334":{"votes":{"MATT HANEY\n(DEM)":676,"MANUEL NORIS-BARRERA\n(REP)":116},"total":792},"7335":{"votes":{"MATT HANEY\n(DEM)":782,"MANUEL NORIS-BARRERA\n(REP)":139},"total":921},"7336":{"votes":{"MATT HANEY\n(DEM)":600,"MANUEL NORIS-BARRERA\n(REP)":137},"total":737},"7337":{"votes":{"MATT HANEY\n(DEM)":277,"MANUEL NORIS-BARRERA\n(REP)":91},"total":368},"7501":{"votes":{"MATT HANEY\n(DEM)":538,"MANUEL NORIS-BARRERA\n(REP)":90},"total":628},"7502":{"votes":{"MATT HANEY\n(DEM)":505,"MANUEL NORIS-BARRERA\n(REP)":77},"total":582},"7503":{"votes":{"MATT HANEY\n(DEM)":682,"MANUEL NORIS-BARRERA\n(REP)":129},"total":811},"7504":{"votes":{"MATT HANEY\n(DEM)":827,"MANUEL NORIS-BARRERA\n(REP)":84},"total":911},"7505":{"votes":{"MATT HANEY\n(DEM)":568,"MANUEL NORIS-BARRERA\n(REP)":70},"total":638},"7506":{"votes":{"MATT HANEY\n(DEM)":619,"MANUEL NORIS-BARRERA\n(REP)":122},"total":741},"7507":{"votes":{"MATT HANEY\n(DEM)":432,"MANUEL NORIS-BARRERA\n(REP)":85},"total":517},"7508":{"votes":{"MATT HANEY\n(DEM)":773,"MANUEL NORIS-BARRERA\n(REP)":64},"total":837},"7509":{"votes":{"MATT HANEY\n(DEM)":545,"MANUEL NORIS-BARRERA\n(REP)":91},"total":636},"7511":{"votes":{"MATT HANEY\n(DEM)":452,"MANUEL NORIS-BARRERA\n(REP)":104},"total":556},"7512":{"votes":{"MATT HANEY\n(DEM)":675,"MANUEL NORIS-BARRERA\n(REP)":114},"total":789},"7513":{"votes":{"MATT HANEY\n(DEM)":898,"MANUEL NORIS-BARRERA\n(REP)":57},"total":955},"7514":{"votes":{"MATT HANEY\n(DEM)":805,"MANUEL NORIS-BARRERA\n(REP)":169},"total":974},"7515":{"votes":{"MATT HANEY\n(DEM)":689,"MANUEL NORIS-BARRERA\n(REP)":93},"total":782},"7516":{"votes":{"MATT HANEY\n(DEM)":699,"MANUEL NORIS-BARRERA\n(REP)":57},"total":756},"7517":{"votes":{"MATT HANEY\n(DEM)":959,"MANUEL NORIS-BARRERA\n(REP)":51},"total":1010},"7518":{"votes":{"MATT HANEY\n(DEM)":737,"MANUEL NORIS-BARRERA\n(REP)":34},"total":771},"7519":{"votes":{"MATT HANEY\n(DEM)":910,"MANUEL NORIS-BARRERA\n(REP)":85},"total":995},"7521":{"votes":{"MATT HANEY\n(DEM)":842,"MANUEL NORIS-BARRERA\n(REP)":55},"total":897},"7522":{"votes":{"MATT HANEY\n(DEM)":797,"MANUEL NORIS-BARRERA\n(REP)":83},"total":880},"7523":{"votes":{"MATT HANEY\n(DEM)":666,"MANUEL NORIS-BARRERA\n(REP)":95},"total":761},"7524":{"votes":{"MATT HANEY\n(DEM)":331,"MANUEL NORIS-BARRERA\n(REP)":91},"total":422},"7525":{"votes":{"MATT HANEY\n(DEM)":430,"MANUEL NORIS-BARRERA\n(REP)":99},"total":529},"7526":{"votes":{"MATT HANEY\n(DEM)":493,"MANUEL NORIS-BARRERA\n(REP)":142},"total":635},"7527":{"votes":{"MATT HANEY\n(DEM)":531,"MANUEL NORIS-BARRERA\n(REP)":124},"total":655},"7528":{"votes":{"MATT HANEY\n(DEM)":309,"MANUEL NORIS-BARRERA\n(REP)":107},"total":416},"7529":{"votes":{"MATT HANEY\n(DEM)":363,"MANUEL NORIS-BARRERA\n(REP)":104},"total":467},"7531":{"votes":{"MATT HANEY\n(DEM)":376,"MANUEL NORIS-BARRERA\n(REP)":95},"total":471},"7532":{"votes":{"MATT HANEY\n(DEM)":511,"MANUEL NORIS-BARRERA\n(REP)":86},"total":597},"7533":{"votes":{"MATT HANEY\n(DEM)":403,"MANUEL NORIS-BARRERA\n(REP)":133},"total":536},"7534":{"votes":{"MATT HANEY\n(DEM)":393,"MANUEL NORIS-BARRERA\n(REP)":86},"total":479},"7601":{"votes":{"MATT HANEY\n(DEM)":546,"MANUEL NORIS-BARRERA\n(REP)":49},"total":595},"7602":{"votes":{"MATT HANEY\n(DEM)":810,"MANUEL NORIS-BARRERA\n(REP)":99},"total":909},"7603":{"votes":{"MATT HANEY\n(DEM)":752,"MANUEL NORIS-BARRERA\n(REP)":120},"total":872},"7604":{"votes":{"MATT HANEY\n(DEM)":555,"MANUEL NORIS-BARRERA\n(REP)":132},"total":687},"7605":{"votes":{"MATT HANEY\n(DEM)":434,"MANUEL NORIS-BARRERA\n(REP)":112},"total":546},"7606":{"votes":{"MATT HANEY\n(DEM)":485,"MANUEL NORIS-BARRERA\n(REP)":102},"total":587},"7607":{"votes":{"MATT HANEY\n(DEM)":406,"MANUEL NORIS-BARRERA\n(REP)":81},"total":487},"7608":{"votes":{"MATT HANEY\n(DEM)":807,"MANUEL NORIS-BARRERA\n(REP)":132},"total":939},"7609":{"votes":{"MATT HANEY\n(DEM)":560,"MANUEL NORIS-BARRERA\n(REP)":109},"total":669},"7611":{"votes":{"MATT HANEY\n(DEM)":399,"MANUEL NORIS-BARRERA\n(REP)":53},"total":452},"7612":{"votes":{"MATT HANEY\n(DEM)":500,"MANUEL NORIS-BARRERA\n(REP)":67},"total":567},"7613":{"votes":{"MATT HANEY\n(DEM)":531,"MANUEL NORIS-BARRERA\n(REP)":99},"total":630},"7614":{"votes":{"MATT HANEY\n(DEM)":393,"MANUEL NORIS-BARRERA\n(REP)":98},"total":491},"7615":{"votes":{"MATT HANEY\n(DEM)":408,"MANUEL NORIS-BARRERA\n(REP)":98},"total":506},"7616":{"votes":{"MATT HANEY\n(DEM)":375,"MANUEL NORIS-BARRERA\n(REP)":71},"total":446},"7617":{"votes":{"MATT HANEY\n(DEM)":463,"MANUEL NORIS-BARRERA\n(REP)":98},"total":561},"7618":{"votes":{"MATT HANEY\n(DEM)":379,"MANUEL NORIS-BARRERA\n(REP)":89},"total":468},"7619":{"votes":{"MATT HANEY\n(DEM)":432,"MANUEL NORIS-BARRERA\n(REP)":90},"total":522},"7621":{"votes":{"MATT HANEY\n(DEM)":417,"MANUEL NORIS-BARRERA\n(REP)":80},"total":497},"7622":{"votes":{"MATT HANEY\n(DEM)":733,"MANUEL NORIS-BARRERA\n(REP)":104},"total":837},"7623":{"votes":{"MATT HANEY\n(DEM)":296,"MANUEL NORIS-BARRERA\n(REP)":65},"total":361},"7624":{"votes":{"MATT HANEY\n(DEM)":418,"MANUEL NORIS-BARRERA\n(REP)":71},"total":489},"7625":{"votes":{"MATT HANEY\n(DEM)":233,"MANUEL NORIS-BARRERA\n(REP)":98},"total":331},"7626":{"votes":{"MATT HANEY\n(DEM)":367,"MANUEL NORIS-BARRERA\n(REP)":89},"total":456},"7627":{"votes":{"MATT HANEY\n(DEM)":474,"MANUEL NORIS-BARRERA\n(REP)":76},"total":550},"7628":{"votes":{"MATT HANEY\n(DEM)":453,"MANUEL NORIS-BARRERA\n(REP)":68},"total":521},"7629":{"votes":{"MATT HANEY\n(DEM)":740,"MANUEL NORIS-BARRERA\n(REP)":117},"total":857},"7631":{"votes":{"MATT HANEY\n(DEM)":659,"MANUEL NORIS-BARRERA\n(REP)":179},"total":838},"7632":{"votes":{"MATT HANEY\n(DEM)":524,"MANUEL NORIS-BARRERA\n(REP)":119},"total":643},"7633":{"votes":{"MATT HANEY\n(DEM)":458,"MANUEL NORIS-BARRERA\n(REP)":103},"total":561},"7634":{"votes":{"MATT HANEY\n(DEM)":644,"MANUEL NORIS-BARRERA\n(REP)":114},"total":758},"7635":{"votes":{"MATT HANEY\n(DEM)":667,"MANUEL NORIS-BARRERA\n(REP)":204},"total":871},"7637":{"votes":{"MATT HANEY\n(DEM)":490,"MANUEL NORIS-BARRERA\n(REP)":134},"total":624},"7638":{"votes":{"MATT HANEY\n(DEM)":452,"MANUEL NORIS-BARRERA\n(REP)":134},"total":586},"7639":{"votes":{"MATT HANEY\n(DEM)":610,"MANUEL NORIS-BARRERA\n(REP)":127},"total":737},"7641":{"votes":{"MATT HANEY\n(DEM)":622,"MANUEL NORIS-BARRERA\n(REP)":157},"total":779},"7642":{"votes":{"MATT HANEY\n(DEM)":593,"MANUEL NORIS-BARRERA\n(REP)":157},"total":750},"7643":{"votes":{"MATT HANEY\n(DEM)":494,"MANUEL NORIS-BARRERA\n(REP)":123},"total":617},"7644":{"votes":{"MATT HANEY\n(DEM)":351,"MANUEL NORIS-BARRERA\n(REP)":104},"total":455},"7645":{"votes":{"MATT HANEY\n(DEM)":391,"MANUEL NORIS-BARRERA\n(REP)":115},"total":506},"7701":{"votes":{"MATT HANEY\n(DEM)":554,"MANUEL NORIS-BARRERA\n(REP)":138},"total":692},"7702":{"votes":{"MATT HANEY\n(DEM)":606,"MANUEL NORIS-BARRERA\n(REP)":122},"total":728},"7703":{"votes":{"MATT HANEY\n(DEM)":696,"MANUEL NORIS-BARRERA\n(REP)":160},"total":856},"7704":{"votes":{"MATT HANEY\n(DEM)":575,"MANUEL NORIS-BARRERA\n(REP)":161},"total":736},"7705":{"votes":{"MATT HANEY\n(DEM)":550,"MANUEL NORIS-BARRERA\n(REP)":193},"total":743},"7706":{"votes":{"MATT HANEY\n(DEM)":588,"MANUEL NORIS-BARRERA\n(REP)":137},"total":725},"7707":{"votes":{"MATT HANEY\n(DEM)":685,"MANUEL NORIS-BARRERA\n(REP)":249},"total":934},"7708":{"votes":{"MATT HANEY\n(DEM)":444,"MANUEL NORIS-BARRERA\n(REP)":236},"total":680},"7709":{"votes":{"MATT HANEY\n(DEM)":610,"MANUEL NORIS-BARRERA\n(REP)":221},"total":831},"7711":{"votes":{"MATT HANEY\n(DEM)":869,"MANUEL NORIS-BARRERA\n(REP)":134},"total":1003},"7712":{"votes":{"MATT HANEY\n(DEM)":404,"MANUEL NORIS-BARRERA\n(REP)":132},"total":536},"7713":{"votes":{"MATT HANEY\n(DEM)":418,"MANUEL NORIS-BARRERA\n(REP)":139},"total":557},"7714":{"votes":{"MATT HANEY\n(DEM)":561,"MANUEL NORIS-BARRERA\n(REP)":155},"total":716},"7715":{"votes":{"MATT HANEY\n(DEM)":728,"MANUEL NORIS-BARRERA\n(REP)":111},"total":839},"7716":{"votes":{"MATT HANEY\n(DEM)":817,"MANUEL NORIS-BARRERA\n(REP)":111},"total":928},"7717":{"votes":{"MATT HANEY\n(DEM)":548,"MANUEL NORIS-BARRERA\n(REP)":163},"total":711},"7718":{"votes":{"MATT HANEY\n(DEM)":541,"MANUEL NORIS-BARRERA\n(REP)":136},"total":677},"7719":{"votes":{"MATT HANEY\n(DEM)":644,"MANUEL NORIS-BARRERA\n(REP)":168},"total":812},"7801":{"votes":{"MATT HANEY\n(DEM)":856,"MANUEL NORIS-BARRERA\n(REP)":72},"total":928},"7802":{"votes":{"MATT HANEY\n(DEM)":887,"MANUEL NORIS-BARRERA\n(REP)":73},"total":960},"7803":{"votes":{"MATT HANEY\n(DEM)":801,"MANUEL NORIS-BARRERA\n(REP)":52},"total":853},"7804":{"votes":{"MATT HANEY\n(DEM)":743,"MANUEL NORIS-BARRERA\n(REP)":58},"total":801},"7805":{"votes":{"MATT HANEY\n(DEM)":920,"MANUEL NORIS-BARRERA\n(REP)":46},"total":966},"7806":{"votes":{"MATT HANEY\n(DEM)":761,"MANUEL NORIS-BARRERA\n(REP)":57},"total":818},"7807":{"votes":{"MATT HANEY\n(DEM)":812,"MANUEL NORIS-BARRERA\n(REP)":70},"total":882},"7808":{"votes":{"MATT HANEY\n(DEM)":807,"MANUEL NORIS-BARRERA\n(REP)":64},"total":871},"7809":{"votes":{"MATT HANEY\n(DEM)":826,"MANUEL NORIS-BARRERA\n(REP)":57},"total":883},"7811":{"votes":{"MATT HANEY\n(DEM)":762,"MANUEL NORIS-BARRERA\n(REP)":54},"total":816},"7812":{"votes":{"MATT HANEY\n(DEM)":919,"MANUEL NORIS-BARRERA\n(REP)":36},"total":955},"7813":{"votes":{"MATT HANEY\n(DEM)":941,"MANUEL NORIS-BARRERA\n(REP)":73},"total":1014},"7814":{"votes":{"MATT HANEY\n(DEM)":759,"MANUEL NORIS-BARRERA\n(REP)":54},"total":813},"7815":{"votes":{"MATT HANEY\n(DEM)":915,"MANUEL NORIS-BARRERA\n(REP)":70},"total":985},"7816":{"votes":{"MATT HANEY\n(DEM)":726,"MANUEL NORIS-BARRERA\n(REP)":52},"total":778},"7817":{"votes":{"MATT HANEY\n(DEM)":774,"MANUEL NORIS-BARRERA\n(REP)":55},"total":829},"7818":{"votes":{"MATT HANEY\n(DEM)":665,"MANUEL NORIS-BARRERA\n(REP)":68},"total":733},"7819":{"votes":{"MATT HANEY\n(DEM)":687,"MANUEL NORIS-BARRERA\n(REP)":89},"total":776},"7821":{"votes":{"MATT HANEY\n(DEM)":893,"MANUEL NORIS-BARRERA\n(REP)":59},"total":952},"7822":{"votes":{"MATT HANEY\n(DEM)":826,"MANUEL NORIS-BARRERA\n(REP)":39},"total":865},"7823":{"votes":{"MATT HANEY\n(DEM)":888,"MANUEL NORIS-BARRERA\n(REP)":101},"total":989},"7824":{"votes":{"MATT HANEY\n(DEM)":809,"MANUEL NORIS-BARRERA\n(REP)":62},"total":871},"7825":{"votes":{"MATT HANEY\n(DEM)":873,"MANUEL NORIS-BARRERA\n(REP)":56},"total":929},"7826":{"votes":{"MATT HANEY\n(DEM)":572,"MANUEL NORIS-BARRERA\n(REP)":71},"total":643},"7827":{"votes":{"MATT HANEY\n(DEM)":663,"MANUEL NORIS-BARRERA\n(REP)":77},"total":740},"7828":{"votes":{"MATT HANEY\n(DEM)":670,"MANUEL NORIS-BARRERA\n(REP)":48},"total":718},"7829":{"votes":{"MATT HANEY\n(DEM)":807,"MANUEL NORIS-BARRERA\n(REP)":68},"total":875},"7831":{"votes":{"MATT HANEY\n(DEM)":877,"MANUEL NORIS-BARRERA\n(REP)":83},"total":960},"7832":{"votes":{"MATT HANEY\n(DEM)":890,"MANUEL NORIS-BARRERA\n(REP)":88},"total":978},"7833":{"votes":{"MATT HANEY\n(DEM)":861,"MANUEL NORIS-BARRERA\n(REP)":61},"total":922},"7834":{"votes":{"MATT HANEY\n(DEM)":912,"MANUEL NORIS-BARRERA\n(REP)":102},"total":1014},"7835":{"votes":{"MATT HANEY\n(DEM)":806,"MANUEL NORIS-BARRERA\n(REP)":52},"total":858},"7836":{"votes":{"MATT HANEY\n(DEM)":691,"MANUEL NORIS-BARRERA\n(REP)":50},"total":741},"7837":{"votes":{"MATT HANEY\n(DEM)":768,"MANUEL NORIS-BARRERA\n(REP)":72},"total":840},"7838":{"votes":{"MATT HANEY\n(DEM)":845,"MANUEL NORIS-BARRERA\n(REP)":138},"total":983},"7839":{"votes":{"MATT HANEY\n(DEM)":596,"MANUEL NORIS-BARRERA\n(REP)":73},"total":669},"7841":{"votes":{"MATT HANEY\n(DEM)":861,"MANUEL NORIS-BARRERA\n(REP)":64},"total":925},"7842":{"votes":{"MATT HANEY\n(DEM)":921,"MANUEL NORIS-BARRERA\n(REP)":99},"total":1020},"7843":{"votes":{"MATT HANEY\n(DEM)":851,"MANUEL NORIS-BARRERA\n(REP)":71},"total":922},"7844":{"votes":{"MATT HANEY\n(DEM)":671,"MANUEL NORIS-BARRERA\n(REP)":89},"total":760},"7845":{"votes":{"MATT HANEY\n(DEM)":734,"MANUEL NORIS-BARRERA\n(REP)":78},"total":812},"7846":{"votes":{"MATT HANEY\n(DEM)":589,"MANUEL NORIS-BARRERA\n(REP)":87},"total":676},"7847":{"votes":{"MATT HANEY\n(DEM)":722,"MANUEL NORIS-BARRERA\n(REP)":71},"total":793},"7848":{"votes":{"MATT HANEY\n(DEM)":596,"MANUEL NORIS-BARRERA\n(REP)":71},"total":667},"7849":{"votes":{"MATT HANEY\n(DEM)":795,"MANUEL NORIS-BARRERA\n(REP)":85},"total":880},"7851":{"votes":{"MATT HANEY\n(DEM)":816,"MANUEL NORIS-BARRERA\n(REP)":69},"total":885},"7852":{"votes":{"MATT HANEY\n(DEM)":781,"MANUEL NORIS-BARRERA\n(REP)":76},"total":857},"7853":{"votes":{"MATT HANEY\n(DEM)":341,"MANUEL NORIS-BARRERA\n(REP)":56},"total":397},"7854":{"votes":{"MATT HANEY\n(DEM)":327,"MANUEL NORIS-BARRERA\n(REP)":61},"total":388},"7901":{"votes":{"MATT HANEY\n(DEM)":555,"MANUEL NORIS-BARRERA\n(REP)":86},"total":641},"7902":{"votes":{"MATT HANEY\n(DEM)":635,"MANUEL NORIS-BARRERA\n(REP)":79},"total":714},"7903":{"votes":{"MATT HANEY\n(DEM)":726,"MANUEL NORIS-BARRERA\n(REP)":70},"total":796},"7904":{"votes":{"MATT HANEY\n(DEM)":451,"MANUEL NORIS-BARRERA\n(REP)":87},"total":538},"7905":{"votes":{"MATT HANEY\n(DEM)":564,"MANUEL NORIS-BARRERA\n(REP)":87},"total":651},"7906":{"votes":{"MATT HANEY\n(DEM)":804,"MANUEL NORIS-BARRERA\n(REP)":128},"total":932},"7907":{"votes":{"MATT HANEY\n(DEM)":791,"MANUEL NORIS-BARRERA\n(REP)":65},"total":856},"7908":{"votes":{"MATT HANEY\n(DEM)":640,"MANUEL NORIS-BARRERA\n(REP)":82},"total":722},"7909":{"votes":{"MATT HANEY\n(DEM)":651,"MANUEL NORIS-BARRERA\n(REP)":82},"total":733},"7911":{"votes":{"MATT HANEY\n(DEM)":622,"MANUEL NORIS-BARRERA\n(REP)":96},"total":718},"7912":{"votes":{"MATT HANEY\n(DEM)":847,"MANUEL NORIS-BARRERA\n(REP)":81},"total":928},"7913":{"votes":{"MATT HANEY\n(DEM)":830,"MANUEL NORIS-BARRERA\n(REP)":90},"total":920},"7914":{"votes":{"MATT HANEY\n(DEM)":724,"MANUEL NORIS-BARRERA\n(REP)":87},"total":811},"7915":{"votes":{"MATT HANEY\n(DEM)":697,"MANUEL NORIS-BARRERA\n(REP)":84},"total":781},"7916":{"votes":{"MATT HANEY\n(DEM)":713,"MANUEL NORIS-BARRERA\n(REP)":85},"total":798},"7917":{"votes":{"MATT HANEY\n(DEM)":720,"MANUEL NORIS-BARRERA\n(REP)":87},"total":807},"7918":{"votes":{"MATT HANEY\n(DEM)":653,"MANUEL NORIS-BARRERA\n(REP)":87},"total":740},"7919":{"votes":{"MATT HANEY\n(DEM)":743,"MANUEL NORIS-BARRERA\n(REP)":84},"total":827},"7921":{"votes":{"MATT HANEY\n(DEM)":648,"MANUEL NORIS-BARRERA\n(REP)":102},"total":750},"7922":{"votes":{"MATT HANEY\n(DEM)":523,"MANUEL NORIS-BARRERA\n(REP)":114},"total":637},"7923":{"votes":{"MATT HANEY\n(DEM)":588,"MANUEL NORIS-BARRERA\n(REP)":78},"total":666},"7924":{"votes":{"MATT HANEY\n(DEM)":752,"MANUEL NORIS-BARRERA\n(REP)":102},"total":854},"7925":{"votes":{"MATT HANEY\n(DEM)":808,"MANUEL NORIS-BARRERA\n(REP)":87},"total":895},"7926":{"votes":{"MATT HANEY\n(DEM)":519,"MANUEL NORIS-BARRERA\n(REP)":57},"total":576},"7927":{"votes":{"MATT HANEY\n(DEM)":839,"MANUEL NORIS-BARRERA\n(REP)":69},"total":908},"7928":{"votes":{"MATT HANEY\n(DEM)":797,"MANUEL NORIS-BARRERA\n(REP)":55},"total":852},"7929":{"votes":{"MATT HANEY\n(DEM)":611,"MANUEL NORIS-BARRERA\n(REP)":61},"total":672},"7931":{"votes":{"MATT HANEY\n(DEM)":569,"MANUEL NORIS-BARRERA\n(REP)":60},"total":629},"7932":{"votes":{"MATT HANEY\n(DEM)":800,"MANUEL NORIS-BARRERA\n(REP)":75},"total":875},"7933":{"votes":{"MATT HANEY\n(DEM)":835,"MANUEL NORIS-BARRERA\n(REP)":89},"total":924},"7934":{"votes":{"MATT HANEY\n(DEM)":578,"MANUEL NORIS-BARRERA\n(REP)":43},"total":621},"7935":{"votes":{"MATT HANEY\n(DEM)":714,"MANUEL NORIS-BARRERA\n(REP)":101},"total":815},"7936":{"votes":{"MATT HANEY\n(DEM)":736,"MANUEL NORIS-BARRERA\n(REP)":87},"total":823},"7937":{"votes":{"MATT HANEY\n(DEM)":644,"MANUEL NORIS-BARRERA\n(REP)":53},"total":697},"7938":{"votes":{"MATT HANEY\n(DEM)":537,"MANUEL NORIS-BARRERA\n(REP)":76},"total":613},"7939":{"votes":{"MATT HANEY\n(DEM)":495,"MANUEL NORIS-BARRERA\n(REP)":108},"total":603},"7941":{"votes":{"MATT HANEY\n(DEM)":490,"MANUEL NORIS-BARRERA\n(REP)":72},"total":562},"7942":{"votes":{"MATT HANEY\n(DEM)":418,"MANUEL NORIS-BARRERA\n(REP)":151},"total":569},"7943":{"votes":{"MATT HANEY\n(DEM)":418,"MANUEL NORIS-BARRERA\n(REP)":194},"total":612},"7944":{"votes":{"MATT HANEY\n(DEM)":435,"MANUEL NORIS-BARRERA\n(REP)":178},"total":613},"7945":{"votes":{"MATT HANEY\n(DEM)":391,"MANUEL NORIS-BARRERA\n(REP)":164},"total":555},"7946":{"votes":{"MATT HANEY\n(DEM)":539,"MANUEL NORIS-BARRERA\n(REP)":167},"total":706},"7947":{"votes":{"MATT HANEY\n(DEM)":395,"MANUEL NORIS-BARRERA\n(REP)":216},"total":611},"7948":{"votes":{"MATT HANEY\n(DEM)":554,"MANUEL NORIS-BARRERA\n(REP)":146},"total":700},"7949":{"votes":{"MATT HANEY\n(DEM)":288,"MANUEL NORIS-BARRERA\n(REP)":101},"total":389}}}